[{"model": "tennis.alias", "pk": 1, "fields": {"dk_name": "Frances Tiafoe", "fd_name": "Frances Tiafoe", "pinn_name": "Frances Tiafoe", "player": 32995}}, {"model": "tennis.alias", "pk": 2, "fields": {"dk_name": "Diego Schwartzman", "fd_name": "Diego Schwartzman", "pinn_name": "Diego Sebastian Schwartzman", "player": 6029}}, {"model": "tennis.alias", "pk": 3, "fields": {"dk_name": "Felix Auger-Aliassime", "fd_name": "Felix Auger-Aliassime", "pinn_name": "Felix Auger Aliassime", "player": 70740}}, {"model": "tennis.alias", "pk": 4, "fields": {"dk_name": "Sloane Stephens", "fd_name": "Sloane Stephens", "pinn_name": "Sloane Stephens", "player": 22597}}, {"model": "tennis.alias", "pk": 5, "fields": {"dk_name": "Alexander Zverev", "fd_name": "Alexander Zverev", "pinn_name": "Alexander Zverev", "player": 644}}, {"model": "tennis.alias", "pk": 6, "fields": {"dk_name": "Rafael Nadal", "fd_name": "Rafael Nadal", "pinn_name": "Rafael Nadal", "player": 4742}}, {"model": "tennis.alias", "pk": 7, "fields": {"dk_name": "Stan Wawrinka", "fd_name": "Stan Wawrinka", "pinn_name": "Stan Wawrinka", "player": 4526}}, {"model": "tennis.alias", "pk": 8, "fields": {"dk_name": "Donna Vekic", "fd_name": "Donna Vekic", "pinn_name": "Donna Vekic", "player": 24426}}, {"model": "tennis.alias", "pk": 9, "fields": {"dk_name": "John Millman", "fd_name": "John Millman", "pinn_name": "John Millman", "player": 5349}}, {"model": "tennis.alias", "pk": 10, "fields": {"dk_name": "Saisai Zheng", "fd_name": "Saisai Zheng", "pinn_name": "Saisai Zheng", "player": 24334}}, {"model": "tennis.alias", "pk": 11, "fields": {"dk_name": "Pablo Cuevas", "fd_name": "Pablo Cuevas", "pinn_name": "Pablo Cuevas", "player": 4654}}, {"model": "tennis.alias", "pk": 12, "fields": {"dk_name": "Johanna Konta", "fd_name": "Johanna Konta", "pinn_name": "Johanna Konta", "player": 24281}}, {"model": "tennis.alias", "pk": 13, "fields": {"dk_name": "Alex De Minaur", "fd_name": "Alex De Minaur", "pinn_name": "Alex De Minaur", "player": 71304}}, {"model": "tennis.alias", "pk": 14, "fields": {"dk_name": "Sofia Kenin", "fd_name": "Sofia Kenin", "pinn_name": "Sofia Kenin", "player": 46473}}, {"model": "tennis.alias", "pk": 15, "fields": {"dk_name": "Mihaela Buzarnescu", "fd_name": "Mihaela Buzarnescu", "pinn_name": "Mihaela Buzarnescu", "player": 24616}}, {"model": "tennis.alias", "pk": 16, "fields": {"dk_name": "Marco Trungelliti", "fd_name": "Marco Trungelliti", "pinn_name": "Marco Trungelliti", "player": 5466}}, {"model": "tennis.alias", "pk": 17, "fields": {"dk_name": "Victoria Azarenka", "fd_name": "Victoria Azarenka", "pinn_name": "Victoria Azarenka", "player": 22348}}, {"model": "tennis.alias", "pk": 18, "fields": {"dk_name": "Monica Puig", "fd_name": "Monica Puig", "pinn_name": "Monica Puig", "player": 22666}}, {"model": "tennis.alias", "pk": 19, "fields": {"dk_name": "John Isner", "fd_name": "John Isner", "pinn_name": "John Isner", "player": 4544}}, {"model": "tennis.alias", "pk": 20, "fields": {"dk_name": "Sam Querrey", "fd_name": "Sam Querrey", "pinn_name": "Sam Querrey", "player": 5016}}, {"model": "tennis.alias", "pk": 21, "fields": {"dk_name": "Tatjana Maria", "fd_name": "Tatjana Maria", "pinn_name": "Tatjana Maria", "player": 46540}}, {"model": "tennis.alias", "pk": 22, "fields": {"dk_name": "Yafan Wang", "fd_name": "Yafan Wang", "pinn_name": "Yafan Wang", "player": 32134}}, {"model": "tennis.alias", "pk": 23, "fields": {"dk_name": "Bianca Vanessa Andreescu", "fd_name": "Bianca Vanessa Andreescu", "pinn_name": "Bianca Andreescu", "player": 50106}}, {"model": "tennis.alias", "pk": 24, "fields": {"dk_name": "Cameron Norrie", "fd_name": "Cameron Norrie", "pinn_name": "Cameron Norrie", "player": 11800}}, {"model": "tennis.alias", "pk": 25, "fields": {"dk_name": "Katie Boulter", "fd_name": "Katie Boulter", "pinn_name": "Katie Boulter", "player": 41579}}, {"model": "tennis.alias", "pk": 26, "fields": {"dk_name": "Thiago Seyboth Wild", "fd_name": "Thiago Seyboth Wild", "pinn_name": "Thiago Seyboth Wild", "player": 82220}}, {"model": "tennis.alias", "pk": 27, "fields": {"dk_name": "Mackenzie Mcdonald", "fd_name": "Mackenzie Mcdonald", "pinn_name": "Mackenzie McDonald", "player": 11441}}, {"model": "tennis.alias", "pk": 28, "fields": {"dk_name": "Varvara Flink", "fd_name": "Varvara Flink", "pinn_name": "Varvara Flink", "player": 24409}}, {"model": "tennis.alias", "pk": 30, "fields": {"dk_name": "Timea Babos", "fd_name": "Timea Babos", "pinn_name": "Timea Babos", "player": 22811}}, {"model": "tennis.alias", "pk": 31, "fields": {"dk_name": "Peter Gojowczyk", "fd_name": "Peter Gojowczyk", "pinn_name": "Peter Gojowczyk", "player": 5367}}, {"model": "tennis.alias", "pk": 32, "fields": {"dk_name": "Christina Mchale", "fd_name": "Christina Mchale", "pinn_name": "Christina Mchale", "player": 22505}}, {"model": "tennis.alias", "pk": 33, "fields": {"dk_name": "Steve Johnson", "fd_name": "Steve Johnson", "pinn_name": "Steve Johnson", "player": 5438}}, {"model": "tennis.alias", "pk": 34, "fields": {"dk_name": "Nick Kyrgios", "fd_name": "Nick Kyrgios", "pinn_name": "Nick Kyrgios", "player": 6387}}, {"model": "tennis.alias", "pk": 35, "fields": {"dk_name": "Beatriz Haddad Maia", "fd_name": "Beatriz Haddad Maia", "pinn_name": "Beatriz Haddad Maia", "player": 31867}}, {"model": "tennis.alias", "pk": 36, "fields": {"dk_name": "David Ferrer", "fd_name": "David Ferrer", "pinn_name": "David Ferrer", "player": 3970}}, {"model": "tennis.alias", "pk": 37, "fields": {"dk_name": "Laslo Djere", "fd_name": "Laslo Djere", "pinn_name": "Laslo Djere", "player": 11498}}, {"model": "tennis.alias", "pk": 38, "fields": {"dk_name": "Malek Jaziri", "fd_name": "Malek Jaziri", "pinn_name": "Malek Jaziri", "player": 4291}}, {"model": "tennis.alias", "pk": 39, "fields": {"dk_name": "Dayana Yastremska", "fd_name": "Dayana Yastremska", "pinn_name": "Dayana Yastremska", "player": 49441}}, {"model": "tennis.alias", "pk": 40, "fields": {"dk_name": "Amanda Anisimova", "fd_name": "Amanda Anisimova", "pinn_name": "Amanda Anisimova", "player": 51679}}, {"model": "tennis.alias", "pk": 41, "fields": {"dk_name": "Katerina Siniakova", "fd_name": "Katerina Siniakova", "pinn_name": "Katerina Siniakova", "player": 42764}}, {"model": "tennis.alias", "pk": 42, "fields": {"dk_name": "Marketa Vondrousova", "fd_name": "Marketa Vondrousova", "pinn_name": "Marketa Vondrousova", "player": 49278}}, {"model": "tennis.alias", "pk": 43, "fields": {"dk_name": "Petra Martic", "fd_name": "Petra Martic", "pinn_name": "Petra Martic", "player": 22527}}, {"model": "tennis.alias", "pk": 44, "fields": {"dk_name": "Bernarda Pera", "fd_name": "Bernarda Pera", "pinn_name": "Bernarda Pera", "player": 41553}}, {"model": "tennis.alias", "pk": 45, "fields": {"dk_name": "Jennifer Brady", "fd_name": "Jennifer Brady", "pinn_name": "Jennifer Brady", "player": 31598}}, {"model": "tennis.alias", "pk": 46, "fields": {"dk_name": "Shuai Zhang", "fd_name": "Shuai Zhang", "pinn_name": "Shuai Zhang", "player": 22494}}, {"model": "tennis.alias", "pk": 47, "fields": {"dk_name": "Barbora Strycova", "fd_name": "Barbora Strycova", "pinn_name": "Barbora Strycova", "player": null}}, {"model": "tennis.alias", "pk": 48, "fields": {"dk_name": "Lauren Davis", "fd_name": "Lauren Davis", "pinn_name": "Lauren Davis", "player": 22657}}, {"model": "tennis.alias", "pk": 49, "fields": {"dk_name": "Sachia Vickery", "fd_name": "Sachia Vickery", "pinn_name": "Sachia Vickery", "player": 26426}}, {"model": "tennis.alias", "pk": 50, "fields": {"dk_name": "Stefanie Voegele", "fd_name": "Stefanie Voegele", "pinn_name": "Stefanie Voegele", "player": 22482}}, {"model": "tennis.alias", "pk": 51, "fields": {"dk_name": "Anna-Karolina Schmiedlova", "fd_name": "Anna-Karolina Schmiedlova", "pinn_name": "Anna Schmiedlova", "player": 26494}}, {"model": "tennis.alias", "pk": 52, "fields": {"dk_name": "Viktorija Golubic", "fd_name": "Viktorija Golubic", "pinn_name": "Viktorija Golubic", "player": 26488}}, {"model": "tennis.alias", "pk": 53, "fields": {"dk_name": "Viktoria Kuzmova", "fd_name": "Viktoria Kuzmova", "pinn_name": "Viktoria Kuzmova", "player": 47667}}, {"model": "tennis.alias", "pk": 54, "fields": {"dk_name": "Nao Hibino", "fd_name": "Nao Hibino", "pinn_name": "Nao Hibino", "player": 42766}}, {"model": "tennis.alias", "pk": 55, "fields": {"dk_name": "Magdalena Rybarikova", "fd_name": "Magdalena Rybarikova", "pinn_name": "Magdalena Rybarikova", "player": 22464}}, {"model": "tennis.alias", "pk": 56, "fields": {"dk_name": "Catherine Mcnally", "fd_name": "Catherine Mcnally", "pinn_name": "Caty Mcnally", "player": 51539}}, {"model": "tennis.alias", "pk": 57, "fields": {"dk_name": "Magda Linette", "fd_name": "Magda Linette", "pinn_name": "Magda Linette", "player": 24749}}, {"model": "tennis.alias", "pk": 58, "fields": {"dk_name": "Laura Siegemund", "fd_name": "Laura Siegemund", "pinn_name": "Laura Siegemund", "player": 22817}}, {"model": "tennis.alias", "pk": 59, "fields": {"dk_name": "Kateryna Kozlova", "fd_name": "Kateryna Kozlova", "pinn_name": "Kateryna Kozlova", "player": 26350}}, {"model": "tennis.alias", "pk": 60, "fields": {"dk_name": "Aleksandra Krunic", "fd_name": "Aleksandra Krunic", "pinn_name": "Aleksandra Krunic", "player": 24296}}, {"model": "tennis.alias", "pk": 61, "fields": {"dk_name": "Daria Gavrilova", "fd_name": "Daria Gavrilova", "pinn_name": "Daria Gavrilova", "player": 22647}}, {"model": "tennis.alias", "pk": 62, "fields": {"dk_name": "Irina-Camelia Begu", "fd_name": "Irina-Camelia Begu", "pinn_name": "Irina-Camelia Begu", "player": 22613}}, {"model": "tennis.alias", "pk": 63, "fields": {"dk_name": "Pauline Parmentier", "fd_name": "Pauline Parmentier", "pinn_name": "Pauline Parmentier", "player": 22283}}, {"model": "tennis.alias", "pk": 64, "fields": {"dk_name": "Vera Lapko", "fd_name": "Vera Lapko", "pinn_name": "Vera Lapko", "player": 47974}}, {"model": "tennis.alias", "pk": 65, "fields": {"dk_name": "Eugenie Bouchard", "fd_name": "Eugenie Bouchard", "pinn_name": "Eugenie Bouchard", "player": 24320}}, {"model": "tennis.alias", "pk": 66, "fields": {"dk_name": "Zarina Diyas", "fd_name": "Zarina Diyas", "pinn_name": "Zarina Diyas", "player": 22645}}, {"model": "tennis.alias", "pk": 67, "fields": {"dk_name": "Elias Ymer", "fd_name": "Elias Ymer", "pinn_name": "Elias Ymer", "player": 11186}}, {"model": "tennis.alias", "pk": 68, "fields": {"dk_name": "Reilly Opelka", "fd_name": "Reilly Opelka", "pinn_name": "Reilly Opelka", "player": 28972}}, {"model": "tennis.alias", "pk": 69, "fields": {"dk_name": "Maria Sakkari", "fd_name": "Maria Sakkari", "pinn_name": "Maria Sakkari", "player": 31963}}, {"model": "tennis.alias", "pk": 70, "fields": {"dk_name": "Ugo Humbert", "fd_name": "Ugo Humbert", "pinn_name": "Ugo Humbert", "player": 70750}}, {"model": "tennis.alias", "pk": 71, "fields": {"dk_name": "Benoit Paire", "fd_name": "Benoit Paire", "pinn_name": "Benoit Paire", "player": 5324}}, {"model": "tennis.alias", "pk": 72, "fields": {"dk_name": "Taylor Townsend", "fd_name": "Taylor Townsend", "pinn_name": "Taylor Townsend", "player": 26428}}, {"model": "tennis.alias", "pk": 73, "fields": {"dk_name": "Ysaline Bonaventure", "fd_name": "Ysaline Bonaventure", "pinn_name": "Ysaline Bonaventure", "player": 28245}}, {"model": "tennis.alias", "pk": 74, "fields": {"dk_name": "Bradley Klahn", "fd_name": "Bradley Klahn", "pinn_name": "Bradley Klahn", "player": 5602}}, {"model": "tennis.alias", "pk": 75, "fields": {"dk_name": "Prajnesh Gunneswaran", "fd_name": "Prajnesh Gunneswaran", "pinn_name": "Prajnesh Gunneswaran", "player": 5422}}, {"model": "tennis.alias", "pk": 76, "fields": {"dk_name": "Maximilian Marterer", "fd_name": "Maximilian Marterer", "pinn_name": "Maximilian Marterer", "player": 9725}}, {"model": "tennis.alias", "pk": 77, "fields": {"dk_name": "Leonardo Mayer", "fd_name": "Leonardo Mayer", "pinn_name": "Leonardo Mayer", "player": 4914}}, {"model": "tennis.alias", "pk": 78, "fields": {"dk_name": "Bjorn Fratangelo", "fd_name": "Bjorn Fratangelo", "pinn_name": "Bjorn Fratangelo", "player": 6202}}, {"model": "tennis.alias", "pk": 79, "fields": {"dk_name": "Jessica Pegula", "fd_name": "Jessica Pegula", "pinn_name": "Jessica Pegula", "player": 24364}}, {"model": "tennis.alias", "pk": 80, "fields": {"dk_name": "Jan-Lennard Struff", "fd_name": "Jan-Lennard Struff", "pinn_name": "Jan-Lennard Struff", "player": 5515}}, {"model": "tennis.alias", "pk": 81, "fields": {"dk_name": "Kirsten Flipkens", "fd_name": "Kirsten Flipkens", "pinn_name": "Kirsten Flipkens", "player": 22361}}, {"model": "tennis.alias", "pk": 82, "fields": {"dk_name": "Evgeniya Rodina", "fd_name": "Evgeniya Rodina", "pinn_name": "Evgeniya Rodina", "player": 22462}}, {"model": "tennis.alias", "pk": 83, "fields": {"dk_name": "Ashleigh Barty", "fd_name": "Ashleigh Barty", "pinn_name": "Ashleigh Barty", "player": 24344}}, {"model": "tennis.alias", "pk": 84, "fields": {"dk_name": "Tomas Berdych", "fd_name": "Tomas Berdych", "pinn_name": "Tomas Berdych", "player": 4606}}, {"model": "tennis.alias", "pk": 85, "fields": {"dk_name": "Garbine Muguruza", "fd_name": "Garbine Muguruza", "pinn_name": "Garbine Muguruza", "player": 24366}}, {"model": "tennis.alias", "pk": 86, "fields": {"dk_name": "Simona Halep", "fd_name": "Simona Halep", "pinn_name": "Simona Halep", "player": 22615}}, {"model": "tennis.alias", "pk": 87, "fields": {"dk_name": "Qiang Wang", "fd_name": "Qiang Wang", "pinn_name": "Qiang Wang", "player": 24412}}, {"model": "tennis.alias", "pk": 88, "fields": {"dk_name": "Andreas Seppi", "fd_name": "Andreas Seppi", "pinn_name": "Andreas Seppi", "player": 4311}}, {"model": "tennis.alias", "pk": 89, "fields": {"dk_name": "Hubert Hurkacz", "fd_name": "Hubert Hurkacz", "pinn_name": "Hubert Hurkacz", "player": 36658}}, {"model": "tennis.alias", "pk": 90, "fields": {"dk_name": "Radu Albot", "fd_name": "Radu Albot", "pinn_name": "Radu Albot", "player": 5420}}, {"model": "tennis.alias", "pk": 91, "fields": {"dk_name": "Ernests Gulbis", "fd_name": "Ernests Gulbis", "pinn_name": "Ernests Gulbis", "player": 5201}}, {"model": "tennis.alias", "pk": 92, "fields": {"dk_name": "Dusan Lajovic", "fd_name": "Dusan Lajovic", "pinn_name": "Dusan Lajovic", "player": 5571}}, {"model": "tennis.alias", "pk": 93, "fields": {"dk_name": "Alexei Popyrin", "fd_name": "Alexei Popyrin", "pinn_name": "Alexei Popyrin", "player": 71973}}, {"model": "tennis.alias", "pk": 94, "fields": {"dk_name": "Denis Istomin", "fd_name": "Denis Istomin", "pinn_name": "Denis Istomin", "player": 4794}}, {"model": "tennis.alias", "pk": 95, "fields": {"dk_name": "Taylor Fritz", "fd_name": "Taylor Fritz", "pinn_name": "Taylor Fritz", "player": 32987}}, {"model": "tennis.alias", "pk": 96, "fields": {"dk_name": "Su-Wei Hsieh", "fd_name": "Su-Wei Hsieh", "pinn_name": "Su-Wei Hsieh", "player": null}}, {"model": "tennis.alias", "pk": 97, "fields": {"dk_name": "Caroline Garcia", "fd_name": "Caroline Garcia", "pinn_name": "Caroline Garcia", "player": 22653}}, {"model": "tennis.alias", "pk": 98, "fields": {"dk_name": "Robin Haase", "fd_name": "Robin Haase", "pinn_name": "Robin Haase", "player": 4894}}, {"model": "tennis.alias", "pk": 99, "fields": {"dk_name": "Jaume Munar", "fd_name": "Jaume Munar", "pinn_name": "Jaume Munar", "player": 70079}}, {"model": "tennis.alias", "pk": 100, "fields": {"dk_name": "Taro Daniel", "fd_name": "Taro Daniel", "pinn_name": "Taro Daniel", "player": 6107}}, {"model": "tennis.alias", "pk": 101, "fields": {"dk_name": "Daria Kasatkina", "fd_name": "Daria Kasatkina", "pinn_name": "Daria Kasatkina", "player": 47532}}, {"model": "tennis.alias", "pk": 102, "fields": {"dk_name": "Alex Bolt", "fd_name": "Alex Bolt", "pinn_name": "Alex Bolt", "player": 6095}}, {"model": "tennis.alias", "pk": 103, "fields": {"dk_name": "Jelena Ostapenko", "fd_name": "Jelena Ostapenko", "pinn_name": "Jelena Ostapenko", "player": 42429}}, {"model": "tennis.alias", "pk": 104, "fields": {"dk_name": "Marius Copil", "fd_name": "Marius Copil", "pinn_name": "Marius Copil", "player": 5644}}, {"model": "tennis.alias", "pk": 105, "fields": {"dk_name": "Daniel Evans", "fd_name": "Daniel Evans", "pinn_name": "Dan Evans", "player": 5543}}, {"model": "tennis.alias", "pk": 106, "fields": {"dk_name": "Donald Young", "fd_name": "Donald Young", "pinn_name": "Donald Young", "player": 5375}}, {"model": "tennis.alias", "pk": 107, "fields": {"dk_name": "Madison Keys", "fd_name": "Madison Keys", "pinn_name": "Madison Keys", "player": 22664}}, {"model": "tennis.alias", "pk": 108, "fields": {"dk_name": "Karolina Pliskova", "fd_name": "Karolina Pliskova", "pinn_name": "Karolina Pliskova", "player": 22749}}, {"model": "tennis.alias", "pk": 109, "fields": {"dk_name": "Anastasija Sevastova", "fd_name": "Anastasija Sevastova", "pinn_name": "Anastasija Sevastova", "player": 22518}}, {"model": "tennis.alias", "pk": 110, "fields": {"dk_name": "Gael Monfils", "fd_name": "Gael Monfils", "pinn_name": "Gael Monfils", "player": 4789}}, {"model": "tennis.alias", "pk": 111, "fields": {"dk_name": "Aryna Sabalenka", "fd_name": "Aryna Sabalenka", "pinn_name": "Aryna Sabalenka", "player": 48454}}, {"model": "tennis.alias", "pk": 112, "fields": {"dk_name": "Angelique Kerber", "fd_name": "Angelique Kerber", "pinn_name": "Angelique Kerber", "player": 22417}}, {"model": "tennis.alias", "pk": 113, "fields": {"dk_name": "Nikoloz Basilashvili", "fd_name": "Nikoloz Basilashvili", "pinn_name": "Nikoloz Basilashvili", "player": 5918}}, {"model": "tennis.alias", "pk": 114, "fields": {"dk_name": "Petra Kvitova", "fd_name": "Petra Kvitova", "pinn_name": "Petra Kvitova", "player": 22469}}, {"model": "tennis.alias", "pk": 115, "fields": {"dk_name": "Borna Coric", "fd_name": "Borna Coric", "pinn_name": "Borna Coric", "player": 6418}}, {"model": "tennis.alias", "pk": 116, "fields": {"dk_name": "Stefanos Tsitsipas", "fd_name": "Stefanos Tsitsipas", "pinn_name": "Stefanos Tsitsipas", "player": 34139}}, {"model": "tennis.alias", "pk": 117, "fields": {"dk_name": "Gilles Simon", "fd_name": "Gilles Simon", "pinn_name": "Gilles Simon", "player": 4467}}, {"model": "tennis.alias", "pk": 118, "fields": {"dk_name": "Miomir Kecmanovic", "fd_name": "Miomir Kecmanovic", "pinn_name": "Miomir Kecmanovic", "player": 71091}}, {"model": "tennis.alias", "pk": 119, "fields": {"dk_name": "Milos Raonic", "fd_name": "Milos Raonic", "pinn_name": "Milos Raonic", "player": 5670}}, {"model": "tennis.alias", "pk": 120, "fields": {"dk_name": "Anastasia Pavlyuchenkova", "fd_name": "Anastasia Pavlyuchenkova", "pinn_name": "Anastasia Pavlyuchenkova", "player": 22429}}, {"model": "tennis.alias", "pk": 121, "fields": {"dk_name": "Lesia Tsurenko", "fd_name": "Lesia Tsurenko", "pinn_name": "Lesia Tsurenko", "player": 22655}}, {"model": "tennis.alias", "pk": 122, "fields": {"dk_name": "Carla Suarez Navarro", "fd_name": "Carla Suarez-Navarro", "pinn_name": "Carla Suarez Navarro", "player": 22471}}, {"model": "tennis.alias", "pk": 123, "fields": {"dk_name": "Anett Kontaveit", "fd_name": "Anett Kontaveit", "pinn_name": "Anett Kontaveit", "player": 28230}}, {"model": "tennis.alias", "pk": 124, "fields": {"dk_name": "Marco Cecchinato", "fd_name": "Marco Cecchinato", "pinn_name": "Marco Cecchinato", "player": 6051}}, {"model": "tennis.alias", "pk": 125, "fields": {"dk_name": "Albert Ramos-Vinolas", "fd_name": "Albert Ramos-Vinolas", "pinn_name": "Albert Ramos-Vinolas", "player": 5070}}, {"model": "tennis.alias", "pk": 126, "fields": {"dk_name": "Ricardas Berankis", "fd_name": "Ricardas Berankis", "pinn_name": "Ricardas Berankis", "player": 5564}}, {"model": "tennis.alias", "pk": 127, "fields": {"dk_name": "Natalia Vikhlyantseva", "fd_name": "Natalia Vikhlyantseva", "pinn_name": "Natalie Vikhlyantseva", "player": 43370}}, {"model": "tennis.alias", "pk": 128, "fields": {"dk_name": "Guido Andreozzi", "fd_name": "Guido Andreozzi", "pinn_name": "Guido Andreozzi", "player": 5805}}, {"model": "tennis.alias", "pk": 129, "fields": {"dk_name": "Philipp Kohlschreiber", "fd_name": "Philipp Kohlschreiber", "pinn_name": "Philipp Kohlschreiber", "player": 4259}}, {"model": "tennis.alias", "pk": 131, "fields": {"dk_name": "Ivo Karlovic", "fd_name": "Ivo Karlovic", "pinn_name": "Ivo Karlovic", "player": 3333}}, {"model": "tennis.alias", "pk": 132, "fields": {"dk_name": "Venus Williams", "fd_name": "Venus Williams", "pinn_name": "Venus Williams", "player": 20916}}, {"model": "tennis.alias", "pk": 133, "fields": {"dk_name": "Ajla Tomljanovic", "fd_name": "Ajla Tomljanovic", "pinn_name": "Ajla Tomljanovic", "player": 22525}}, {"model": "tennis.alias", "pk": 134, "fields": {"dk_name": "Yulia Putintseva", "fd_name": "Yulia Putintseva", "pinn_name": "Yulia Putintseva", "player": 22844}}, {"model": "tennis.alias", "pk": 135, "fields": {"dk_name": "Marcos Giron", "fd_name": "Marcos Giron", "pinn_name": "Marcos Giron", "player": 6204}}, {"model": "tennis.alias", "pk": 136, "fields": {"dk_name": "Madison Brengle", "fd_name": "Madison Brengle", "pinn_name": "Madison Brengle", "player": 22397}}, {"model": "tennis.alias", "pk": 137, "fields": {"dk_name": "Misaki Doi", "fd_name": "Misaki Doi", "pinn_name": "Misaki Doi", "player": 22617}}, {"model": "tennis.alias", "pk": 138, "fields": {"dk_name": "Mona Barthel", "fd_name": "Mona Barthel", "pinn_name": "Mona Barthel", "player": 22668}}, {"model": "tennis.alias", "pk": 139, "fields": {"dk_name": "Roger Federer", "fd_name": "Roger Federer", "pinn_name": "Roger Federer", "player": 3819}}, {"model": "tennis.alias", "pk": 140, "fields": {"dk_name": "Kei Nishikori", "fd_name": "Kei Nishikori", "pinn_name": "Kei Nishikori", "player": 5442}}, {"model": "tennis.alias", "pk": 141, "fields": {"dk_name": "Elina Svitolina", "fd_name": "Elina Svitolina", "pinn_name": "Elina Svitolina", "player": 24416}}, {"model": "tennis.alias", "pk": 142, "fields": {"dk_name": "Marin Cilic", "fd_name": "Marin Cilic", "pinn_name": "Marin Cilic", "player": 5220}}, {"model": "tennis.alias", "pk": 143, "fields": {"dk_name": "Daniil Medvedev", "fd_name": "Daniil Medvedev", "pinn_name": "Daniil Medvedev", "player": 6407}}, {"model": "tennis.alias", "pk": 144, "fields": {"dk_name": "Karen Khachanov", "fd_name": "Karen Khachanov", "pinn_name": "Karen Khachanov", "player": 11560}}, {"model": "tennis.alias", "pk": 145, "fields": {"dk_name": "Kyle Edmund", "fd_name": "Kyle Edmund", "pinn_name": "Kyle Edmund", "player": 6364}}, {"model": "tennis.alias", "pk": 146, "fields": {"dk_name": "Serena Williams", "fd_name": "Serena Williams", "pinn_name": "Serena Williams", "player": 19494}}, {"model": "tennis.alias", "pk": 147, "fields": {"dk_name": "David Goffin", "fd_name": "David Goffin", "pinn_name": "David Goffin", "player": 5663}}, {"model": "tennis.alias", "pk": 148, "fields": {"dk_name": "Kiki Bertens", "fd_name": "Kiki Bertens", "pinn_name": "Kiki Bertens", "player": 24283}}, {"model": "tennis.alias", "pk": 149, "fields": {"dk_name": "Guido Pella", "fd_name": "Guido Pella", "pinn_name": "Guido Pella", "player": 5539}}, {"model": "tennis.alias", "pk": 150, "fields": {"dk_name": "Denis Shapovalov", "fd_name": "Denis Shapovalov", "pinn_name": "Denis Shapovalov", "player": 47464}}, {"model": "tennis.alias", "pk": 151, "fields": {"dk_name": "Andrey Rublev", "fd_name": "Andrey Rublev", "pinn_name": "Andrey Rublev", "player": 32769}}, {"model": "tennis.alias", "pk": 152, "fields": {"dk_name": "Elise Mertens", "fd_name": "Elise Mertens", "pinn_name": "Elise Mertens", "player": 40804}}, {"model": "tennis.alias", "pk": 153, "fields": {"dk_name": "Lucas Pouille", "fd_name": "Lucas Pouille", "pinn_name": "Lucas Pouille", "player": 6284}}, {"model": "tennis.alias", "pk": 154, "fields": {"dk_name": "Fabio Fognini", "fd_name": "Fabio Fognini", "pinn_name": "Fabio Fognini", "player": 4921}}, {"model": "tennis.alias", "pk": 155, "fields": {"dk_name": "Filip Krajinovic", "fd_name": "Filip Krajinovic", "pinn_name": "Filip Krajinovic", "player": 5922}}, {"model": "tennis.alias", "pk": 156, "fields": {"dk_name": "Marton Fucsovics", "fd_name": "Marton Fucsovics", "pinn_name": "Marton Fucsovics", "player": 5902}}, {"model": "tennis.alias", "pk": 157, "fields": {"dk_name": "Nicolas Jarry", "fd_name": "Nicolas Jarry", "pinn_name": "Nicolas Jarry", "player": 11782}}, {"model": "tennis.alias", "pk": 158, "fields": {"dk_name": "Roberto Carballes Baena", "fd_name": "Roberto Carballes Baena", "pinn_name": "Roberto Carballes Baena", "player": 6134}}, {"model": "tennis.alias", "pk": 159, "fields": {"dk_name": "Adrian Mannarino", "fd_name": "Adrian Mannarino", "pinn_name": "Adrian Mannarino", "player": 5166}}, {"model": "tennis.alias", "pk": 160, "fields": {"dk_name": "Jared Donaldson", "fd_name": "Jared Donaldson", "pinn_name": "Jared Donaldson", "player": 11562}}, {"model": "tennis.alias", "pk": 161, "fields": {"dk_name": "Novak Djokovic", "fd_name": "Novak Djokovic", "pinn_name": "Novak Djokovic", "player": 4920}}, {"model": "tennis.alias", "pk": 162, "fields": {"dk_name": "Naomi Osaka", "fd_name": "Naomi Osaka", "pinn_name": "Naomi Osaka", "player": 42902}}, {"model": "tennis.alias", "pk": 163, "fields": {"dk_name": "Julia Goerges", "fd_name": "Julia Goerges", "pinn_name": "Julia Goerges", "player": 22438}}, {"model": "tennis.alias", "pk": 164, "fields": {"dk_name": "Dominic Thiem", "fd_name": "Dominic Thiem", "pinn_name": "Dominic Thiem", "player": 6219}}, {"model": "tennis.alias", "pk": 165, "fields": {"dk_name": "Belinda Bencic", "fd_name": "Belinda Bencic", "pinn_name": "Belinda Bencic", "player": 24437}}, {"model": "tennis.alias", "pk": 166, "fields": {"dk_name": "Yoshihito Nishioka", "fd_name": "Yoshihito Nishioka", "pinn_name": "Yoshihito Nishioka", "player": 6401}}, {"model": "tennis.alias", "pk": 167, "fields": {"dk_name": "Ekaterina Alexandrova", "fd_name": "Ekaterina Alexandrova", "pinn_name": "Ekaterina Alexandrova", "player": 32225}}, {"model": "tennis.alias", "pk": 169, "fields": {"dk_name": "Whitney Osuigwe", "fd_name": "Whitney Osuigwe", "pinn_name": "Whitney Osuigwe", "player": 51356}}, {"model": "tennis.alias", "pk": 170, "fields": {"dk_name": "Margarita Gasparyan", "fd_name": "Margarita Gasparyan", "pinn_name": "Margarita Gasparyan", "player": 24439}}, {"model": "tennis.alias", "pk": 171, "fields": {"dk_name": "Samantha Stosur", "fd_name": "Samantha Stosur", "pinn_name": "Sam Stosur", "player": 22080}}, {"model": "tennis.alias", "pk": 172, "fields": {"dk_name": "Sara Sorribes Tormo", "fd_name": "Sara Sorribes Tormo", "pinn_name": "Sara Sorribes Tormo", "player": 28232}}, {"model": "tennis.alias", "pk": 173, "fields": {"dk_name": "Kristina Mladenovic", "fd_name": "Kristina Mladenovic", "pinn_name": "Kristina Mladenovic", "player": 22507}}, {"model": "tennis.alias", "pk": 174, "fields": {"dk_name": "Olga Danilovic", "fd_name": "Olga Danilovic", "pinn_name": "Olga Danilovic", "player": 50041}}, {"model": "tennis.alias", "pk": 175, "fields": {"dk_name": "Xiyu Wang", "fd_name": "Xiyu Wang", "pinn_name": "Xiyu Wang", "player": 51404}}, {"model": "tennis.alias", "pk": 176, "fields": {"dk_name": "Andrea Petkovic", "fd_name": "Andrea Petkovic", "pinn_name": "Andrea Petkovic", "player": 22415}}, {"model": "tennis.alias", "pk": 177, "fields": {"dk_name": "Mari Osaka", "fd_name": "Mari Osaka", "pinn_name": "Mari Osaka", "player": 42145}}, {"model": "tennis.alias", "pk": 178, "fields": {"dk_name": "Anna-Lena Friedsam", "fd_name": "Anna-Lena Friedsam", "pinn_name": "Anna-Lena Friedsam", "player": null}}, {"model": "tennis.alias", "pk": 179, "fields": {"dk_name": "Mikhail Kukushkin", "fd_name": "Mikhail Kukushkin", "pinn_name": "Mikhail Kukushkin", "player": 5055}}, {"model": "tennis.alias", "pk": 180, "fields": {"dk_name": "Denis Kudla", "fd_name": "Denis Kudla", "pinn_name": "Denis Kudla", "player": 6031}}, {"model": "tennis.alias", "pk": 181, "fields": {"dk_name": "Ilya Ivashka", "fd_name": "Ilya Ivashka", "pinn_name": "Ilya Ivashka", "player": 32191}}, {"model": "tennis.alias", "pk": 182, "fields": {"dk_name": "Matteo Berrettini", "fd_name": "Matteo Berrettini", "pinn_name": "Matteo Berrettini", "player": 33806}}, {"model": "tennis.alias", "pk": 183, "fields": {"dk_name": "Thomas Fabbiano", "fd_name": "Thomas Fabbiano", "pinn_name": "Thomas Fabbiano", "player": 5333}}, {"model": "tennis.alias", "pk": 184, "fields": {"dk_name": "Janko Tipsarevic", "fd_name": "Janko Tipsarevic", "pinn_name": "Janko Tipsarevic", "player": 4385}}, {"model": "tennis.alias", "pk": 185, "fields": {"dk_name": "Federico Delbonis", "fd_name": "Federico Delbonis", "pinn_name": "Federico Delbonis", "player": 5630}}, {"model": "tennis.alias", "pk": 186, "fields": {"dk_name": "Dominika Cibulkova", "fd_name": "Dominika Cibulkova", "pinn_name": "Dominika Cibulkova", "player": 22422}}, {"model": "tennis.alias", "pk": 187, "fields": {"dk_name": "Bernard Tomic", "fd_name": "Bernard Tomic", "pinn_name": "Bernard Tomic", "player": 6057}}, {"model": "tennis.alias", "pk": 188, "fields": {"dk_name": "Joao Sousa", "fd_name": "Joao Sousa", "pinn_name": "Joao Sousa", "player": 5303}}, {"model": "tennis.alias", "pk": 189, "fields": {"dk_name": "Monica Niculescu", "fd_name": "Monica Niculescu", "pinn_name": "Monica Niculescu", "player": 22454}}, {"model": "tennis.alias", "pk": 190, "fields": {"dk_name": "Karolina Muchova", "fd_name": "Karolina Muchova", "pinn_name": "Karolina Muchova", "player": 47560}}, {"model": "tennis.alias", "pk": 191, "fields": {"dk_name": "Tamara Zidansek", "fd_name": "Tamara Zidansek", "pinn_name": "Tamara Zidansek", "player": 48288}}, {"model": "tennis.alias", "pk": 192, "fields": {"dk_name": "Pierre-Hugues Herbert", "fd_name": "Pierre-Hugues Herbert", "pinn_name": "Pierre-Hugues Herbert", "player": null}}, {"model": "tennis.alias", "pk": 193, "fields": {"dk_name": "Aljaz Bedene", "fd_name": "Aljaz Bedene", "pinn_name": "Aljaz Bedene", "player": 5370}}, {"model": "tennis.alias", "pk": 194, "fields": {"dk_name": "Chun Hsin Tseng", "fd_name": "Chun Hsin Tseng", "pinn_name": "Chun Hsin Tseng", "player": 75448}}, {"model": "tennis.alias", "pk": 195, "fields": {"dk_name": "Pablo Andujar", "fd_name": "Pablo Andujar", "pinn_name": "Pablo Andujar", "player": 4664}}, {"model": "tennis.alias", "pk": 196, "fields": {"dk_name": "Roberto Bautista Agut", "fd_name": "Roberto Bautista Agut", "pinn_name": "Roberto Bautista Agut", "player": 5131}}, {"model": "tennis.alias", "pk": 197, "fields": {"dk_name": "Camila Giorgi", "fd_name": "Camila Giorgi", "pinn_name": "Camila Giorgi", "player": 24285}}, {"model": "tennis.alias", "pk": 198, "fields": {"dk_name": "Alize Cornet", "fd_name": "Alize Cornet", "pinn_name": "Alize Cornet", "player": 22285}}, {"model": "tennis.alias", "pk": 199, "fields": {"dk_name": "Alexander Bublik", "fd_name": "Alexander Bublik", "pinn_name": "Alexander Bublik", "player": 25214}}, {"model": "tennis.alias", "pk": 200, "fields": {"dk_name": "Lorenzo Sonego", "fd_name": "Lorenzo Sonego", "pinn_name": "Lorenzo Sonego", "player": 45169}}, {"model": "tennis.alias", "pk": 201, "fields": {"dk_name": "Rebecca Peterson", "fd_name": "Rebecca Peterson", "pinn_name": "Rebecca Peterson", "player": 24407}}, {"model": "tennis.alias", "pk": 202, "fields": {"dk_name": "Caroline Wozniacki", "fd_name": "Caroline Wozniacki", "pinn_name": "Caroline Wozniacki", "player": 22424}}, {"model": "tennis.alias", "pk": 203, "fields": {"dk_name": "Kevin Anderson", "fd_name": "Kevin Anderson", "pinn_name": "Kevin Anderson", "player": 4728}}, {"model": "tennis.alias", "pk": 204, "fields": {"dk_name": "Grigor Dimitrov", "fd_name": "Grigor Dimitrov", "pinn_name": "Grigor Dimitrov", "player": 5763}}, {"model": "tennis.alias", "pk": 205, "fields": {"dk_name": "Damir Dzumhur", "fd_name": "Damir Dzumhur", "pinn_name": "Damir Dzumhur", "player": 5986}}, {"model": "tennis.alias", "pk": 206, "fields": {"dk_name": "Jordan Thompson", "fd_name": "Jordan Thompson", "pinn_name": "Jordan Thompson", "player": 11427}}, {"model": "tennis.alias", "pk": 207, "fields": {"dk_name": "Jeremy Chardy", "fd_name": "Jeremy Chardy", "pinn_name": "Jeremy Chardy", "player": 4868}}, {"model": "tennis.alias", "pk": 208, "fields": {"dk_name": "Polona Hercog", "fd_name": "Polona Hercog", "pinn_name": "Polona Hercog", "player": 22539}}, {"model": "tennis.alias", "pk": 209, "fields": {"dk_name": "Nadiia Kichenok", "fd_name": "Nadiia Kichenok", "pinn_name": "Nadiya Kichenok", "player": 26016}}, {"model": "tennis.alias", "pk": 210, "fields": {"dk_name": "Aliona Bolsova Zadoinov", "fd_name": "Aliona Bolsova Zadoinov", "pinn_name": "Aliona Bolsova Zadoinov", "player": null}}, {"model": "tennis.alias", "pk": 211, "fields": {"dk_name": "Martina Trevisan", "fd_name": "Martina Trevisan", "pinn_name": "Martina Trevisan", "player": 26130}}, {"model": "tennis.alias", "pk": 212, "fields": {"dk_name": "Francesca Di Lorenzo", "fd_name": "Francesca Di Lorenzo", "pinn_name": "Francesca Di Lorenzo", "player": 50108}}, {"model": "tennis.alias", "pk": 213, "fields": {"dk_name": "Astra Sharma", "fd_name": "Astra Sharma", "pinn_name": "Astra Sharma", "player": 31969}}, {"model": "tennis.alias", "pk": 214, "fields": {"dk_name": "Ivana Jorovic", "fd_name": "Ivana Jorovic", "pinn_name": "Ivana Jorovic", "player": 42837}}, {"model": "tennis.alias", "pk": 215, "fields": {"dk_name": "Allie Kiick", "fd_name": "Allie Kiick", "pinn_name": "Allie Kiick", "player": 46434}}, {"model": "tennis.alias", "pk": 216, "fields": {"dk_name": "Mandy Minella", "fd_name": "Mandy Minella", "pinn_name": "Mandy Minella", "player": 22636}}, {"model": "tennis.alias", "pk": 217, "fields": {"dk_name": "Shelby Rogers", "fd_name": "Shelby Rogers", "pinn_name": "Shelby Rogers", "player": 22632}}, {"model": "tennis.alias", "pk": 218, "fields": {"dk_name": "Sara Errani", "fd_name": "Sara Errani", "pinn_name": "Sara Errani", "player": 22442}}, {"model": "tennis.alias", "pk": 219, "fields": {"dk_name": "Ana Bogdan", "fd_name": "Ana Bogdan", "pinn_name": "Ana Bogdan", "player": 24497}}, {"model": "tennis.alias", "pk": 220, "fields": {"dk_name": "Giuliana Olmos", "fd_name": "Giuliana Olmos", "pinn_name": "Giuliana Olmos", "player": 31166}}, {"model": "tennis.alias", "pk": 221, "fields": {"dk_name": "Destanee Aiava", "fd_name": "Destanee Aiava", "pinn_name": "Destanee Aiava", "player": 49407}}, {"model": "tennis.alias", "pk": 222, "fields": {"dk_name": "Johanna Larsson", "fd_name": "Johanna Larsson", "pinn_name": "Johanna Larsson", "player": 22619}}, {"model": "tennis.alias", "pk": 223, "fields": {"dk_name": "Victoria Rodriguez", "fd_name": "Victoria Rodriguez", "pinn_name": "Victoria Rodriguez", "player": 43115}}, {"model": "tennis.alias", "pk": 224, "fields": {"dk_name": "Lara Arruabarrena", "fd_name": "Lara Arruabarrena-Vecino", "pinn_name": "Lara Arruabarrena", "player": 24264}}, {"model": "tennis.alias", "pk": 225, "fields": {"dk_name": "Alison Riske", "fd_name": "Alison Riske", "pinn_name": "Alison Riske", "player": 22607}}, {"model": "tennis.alias", "pk": 226, "fields": {"dk_name": "Dalila Jakupovic", "fd_name": "Dalila Jakupovic", "pinn_name": "Dalila Jakupovic", "player": 26296}}, {"model": "tennis.alias", "pk": 227, "fields": {"dk_name": "Harriet Dart", "fd_name": "Harriet Dart", "pinn_name": "Harriet Dart", "player": 41921}}, {"model": "tennis.alias", "pk": 228, "fields": {"dk_name": "Conny Perrin", "fd_name": "Conny Perrin", "pinn_name": "Conny Perrin", "player": 24275}}, {"model": "tennis.alias", "pk": 229, "fields": {"dk_name": "Anna Blinkova", "fd_name": "Anna Blinkova", "pinn_name": "Anna Blinkova", "player": 49411}}, {"model": "tennis.alias", "pk": 230, "fields": {"dk_name": "Greta Arn", "fd_name": "Greta Arn", "pinn_name": "Greta Arn", "player": 21603}}, {"model": "tennis.alias", "pk": 231, "fields": {"dk_name": "Shilin Xu", "fd_name": "Shilin Xu", "pinn_name": "Shilin Xu", "player": 42801}}, {"model": "tennis.alias", "pk": 232, "fields": {"dk_name": "Renata Zarazua", "fd_name": "Renata Zarazua", "pinn_name": "Renata Zarazua", "player": 47146}}, {"model": "tennis.alias", "pk": 233, "fields": {"dk_name": "Elena-Gabriela Ruse", "fd_name": "Elena-Gabriela Ruse", "pinn_name": "Elena-Gabriela Ruse", "player": 43000}}, {"model": "tennis.alias", "pk": 234, "fields": {"dk_name": "Kristina Kucova", "fd_name": "Kristina Kucova", "pinn_name": "Kristina Kucova", "player": 22564}}, {"model": "tennis.alias", "pk": 235, "fields": {"dk_name": "Miyu Kato", "fd_name": "Miyu Kato", "pinn_name": "Miyu Kato", "player": 26434}}, {"model": "tennis.alias", "pk": 236, "fields": {"dk_name": "Emma Navarro", "fd_name": "Emma Navarro", "pinn_name": "Emma Navarro", "player": 50593}}, {"model": "tennis.alias", "pk": 237, "fields": {"dk_name": "Kaia Kanepi", "fd_name": "Kaia Kanepi", "pinn_name": "Kaia Kanepi", "player": 22363}}, {"model": "tennis.alias", "pk": 238, "fields": {"dk_name": "Maria Camila Osorio Serrano", "fd_name": "Maria Camila Osorio Serrano", "pinn_name": "Maria Camila Osorio Serrano", "player": null}}, {"model": "tennis.alias", "pk": 239, "fields": {"dk_name": "Casper Ruud", "fd_name": "Casper Ruud", "pinn_name": "Casper Ruud", "player": 50147}}, {"model": "tennis.alias", "pk": 240, "fields": {"dk_name": "Varvara Lepchenko", "fd_name": "Varvara Lepchenko", "pinn_name": "Varvara Lepchenko", "player": 22387}}, {"model": "tennis.alias", "pk": 241, "fields": {"dk_name": "Jasmine Paolini", "fd_name": "Jasmine Paolini", "pinn_name": "Jasmine Paolini", "player": 41661}}, {"model": "tennis.alias", "pk": 242, "fields": {"dk_name": "Marcel Granollers", "fd_name": "Marcel Granollers", "pinn_name": "Marcel Granollers", "player": 4716}}, {"model": "tennis.alias", "pk": 243, "fields": {"dk_name": "Ryan Harrison", "fd_name": "Ryan Harrison", "pinn_name": "Ryan Harrison", "player": 5978}}, {"model": "tennis.alias", "pk": 244, "fields": {"dk_name": "Cristian Garin", "fd_name": "Cristian Garin", "pinn_name": "Cristian Garin", "player": 6412}}, {"model": "tennis.alias", "pk": 245, "fields": {"dk_name": "Elitsa Kostova", "fd_name": "Elitsa Kostova", "pinn_name": "Elitsa Kostova", "player": 24362}}, {"model": "tennis.alias", "pk": 246, "fields": {"dk_name": "Hugo Dellien", "fd_name": "Hugo Dellien", "pinn_name": "Hugo Dellien", "player": 6184}}, {"model": "tennis.alias", "pk": 247, "fields": {"dk_name": "Sabine Lisicki", "fd_name": "Sabine Lisicki", "pinn_name": "Sabine Lisicki", "player": 22456}}, {"model": "tennis.alias", "pk": 248, "fields": {"dk_name": "Kristie Haerim Ahn", "fd_name": "Kristie Haerim Ahn", "pinn_name": "Kristie Ahn", "player": 22486}}, {"model": "tennis.alias", "pk": 249, "fields": {"dk_name": "Daniel Elahi Galan", "fd_name": "Daniel Elahi Galan", "pinn_name": "Daniel Elahi Galan", "player": null}}, {"model": "tennis.alias", "pk": 250, "fields": {"dk_name": "Guillermo Garcia-Lopez", "fd_name": "Guillermo Garcia-Lopez", "pinn_name": "Guillermo Garcia-Lopez", "player": null}}, {"model": "tennis.alias", "pk": 251, "fields": {"dk_name": "Antonia Lottner", "fd_name": "Antonia Lottner", "pinn_name": "Antonia Lottner", "player": 28238}}, {"model": "tennis.alias", "pk": 252, "fields": {"dk_name": "Paolo Lorenzi", "fd_name": "Paolo Lorenzi", "pinn_name": "Paolo Lorenzi", "player": 3893}}, {"model": "tennis.alias", "pk": 253, "fields": {"dk_name": "Tennys Sandgren", "fd_name": "Tennys Sandgren", "pinn_name": "Tennys Sandgren", "player": 5801}}, {"model": "tennis.alias", "pk": 254, "fields": {"dk_name": "Bibiane Schoofs", "fd_name": "Bibiane Schoofs", "pinn_name": "Bibiane Schoofs", "player": 24342}}, {"model": "tennis.alias", "pk": 255, "fields": {"dk_name": "Santiago Giraldo", "fd_name": "Santiago Giraldo", "pinn_name": "Santiago Giraldo", "player": 5046}}, {"model": "tennis.alias", "pk": 256, "fields": {"dk_name": "Noah Rubin", "fd_name": "Noah Rubin", "pinn_name": "Noah Rubin", "player": 11496}}, {"model": "tennis.alias", "pk": 257, "fields": {"dk_name": "Pedja Krstin", "fd_name": "Pedja Krstin", "pinn_name": "Pedja Krstin", "player": 6339}}, {"model": "tennis.alias", "pk": 258, "fields": {"dk_name": "Henri Laaksonen", "fd_name": "Henri Laaksonen", "pinn_name": "Henri Laaksonen", "player": 5953}}, {"model": "tennis.alias", "pk": 259, "fields": {"dk_name": "Irina Khromacheva", "fd_name": "Irina Khromacheva", "pinn_name": "Irina Khromacheva", "player": 24822}}, {"model": "tennis.alias", "pk": 260, "fields": {"dk_name": "Hiroko Kuwata", "fd_name": "Hiroko Kuwata", "pinn_name": "Hiroko Kuwata", "player": 31532}}, {"model": "tennis.alias", "pk": 261, "fields": {"dk_name": "Emiliana Arango", "fd_name": "Emiliana Arango", "pinn_name": "Emiliana Arango", "player": 49979}}, {"model": "tennis.alias", "pk": 262, "fields": {"dk_name": "Timea Bacsinszky", "fd_name": "Timea Bacsinszky", "pinn_name": "Timea Bacsinszky", "player": 22411}}, {"model": "tennis.alias", "pk": 263, "fields": {"dk_name": "Svetlana Kuznetsova", "fd_name": "Svetlana Kuznetsova", "pinn_name": "Svetlana Kuznetsova", "player": 22071}}, {"model": "tennis.alias", "pk": 264, "fields": {"dk_name": "Jo-Wilfried Tsonga", "fd_name": "Jo-Wilfried Tsonga", "pinn_name": "Jo-Wilfried Tsonga", "player": 4541}}, {"model": "tennis.alias", "pk": 265, "fields": {"dk_name": "Kristyna Pliskova", "fd_name": "Kristyna Pliskova", "pinn_name": "Kristyna Pliskova", "player": 22819}}, {"model": "tennis.alias", "pk": 266, "fields": {"dk_name": "Pemra Ozgen", "fd_name": "Pemra Ozgen", "pinn_name": "Pemra Ozgen", "player": 22753}}, {"model": "tennis.alias", "pk": 267, "fields": {"dk_name": "Fernando Verdasco", "fd_name": "Fernando Verdasco", "pinn_name": "Fernando Verdasco", "player": 4269}}, {"model": "tennis.alias", "pk": 268, "fields": {"dk_name": "Sergiy Stakhovsky", "fd_name": "Sergiy Stakhovsky", "pinn_name": "Sergiy Stakhovsky", "player": 4659}}, {"model": "tennis.alias", "pk": 269, "fields": {"dk_name": "Juan Ignacio Londero", "fd_name": "Juan Ignacio Londero", "pinn_name": "Juan Ignacio Londero", "player": null}}, {"model": "tennis.alias", "pk": 270, "fields": {"dk_name": "Pedro Sousa", "fd_name": "Pedro Sousa", "pinn_name": "Pedro Sousa", "player": 5148}}, {"model": "tennis.alias", "pk": 271, "fields": {"dk_name": "Greet Minnen", "fd_name": "Greet Minnen", "pinn_name": "Greetje Minnen", "player": 47150}}, {"model": "tennis.alias", "pk": 272, "fields": {"dk_name": "Veronika Kudermetova", "fd_name": "Veronika Kudermetova", "pinn_name": "Veronika Kudermetova", "player": 32121}}, {"model": "tennis.alias", "pk": 273, "fields": {"dk_name": "Mate Valkusz", "fd_name": "Mate Valkusz", "pinn_name": "Mate Valkusz", "player": 71177}}, {"model": "tennis.alias", "pk": 274, "fields": {"dk_name": "Cagla Buyukakcay", "fd_name": "Cagla Buyukakcay", "pinn_name": "Cagla Buyukakcay", "player": 22757}}, {"model": "tennis.alias", "pk": 275, "fields": {"dk_name": "Pablo Carreno Busta", "fd_name": "Pablo Carreno Busta", "pinn_name": "Pablo Carreno-Busta", "player": 5793}}, {"model": "tennis.alias", "pk": 276, "fields": {"dk_name": "Richard Gasquet", "fd_name": "Richard Gasquet", "pinn_name": "Richard Gasquet", "player": 4752}}, {"model": "tennis.alias", "pk": 277, "fields": {"dk_name": "Elisabetta Cocciaretto", "fd_name": "Elisabetta Cocciaretto", "pinn_name": "Elisabetta Cocciaretto", "player": 60765}}, {"model": "tennis.alias", "pk": 278, "fields": {"dk_name": "Sorana Cirstea", "fd_name": "Sorana Cirstea", "pinn_name": "Sorana Cirstea", "player": 22458}}, {"model": "tennis.alias", "pk": 279, "fields": {"dk_name": "Nina Stojanovic", "fd_name": "Nina Stojanovic", "pinn_name": "Nina Stojanovic", "player": 42187}}, {"model": "tennis.alias", "pk": 280, "fields": {"dk_name": "Marta Kostyuk", "fd_name": "Marta Kostyuk", "pinn_name": "Marta Kostyuk", "player": 51665}}, {"model": "tennis.alias", "pk": 281, "fields": {"dk_name": "Fiona Ferro", "fd_name": "Fiona Ferro", "pinn_name": "Fiona Ferro", "player": 42441}}, {"model": "tennis.alias", "pk": 282, "fields": {"dk_name": "Alison Van Uytvanck", "fd_name": "Alison van Uytvanck", "pinn_name": "Alison Van Uytvanck", "player": 24270}}, {"model": "tennis.alias", "pk": 283, "fields": {"dk_name": "Jiri Vesely", "fd_name": "Jiri Vesely", "pinn_name": "Jiri Vesely", "player": 6196}}, {"model": "tennis.alias", "pk": 284, "fields": {"dk_name": "Aliaksandra Sasnovich", "fd_name": "Aliaksandra Sasnovich", "pinn_name": "Aliaksandra Sasnovich", "player": 31232}}, {"model": "tennis.alias", "pk": 285, "fields": {"dk_name": "Sofya Zhuk", "fd_name": "Sofya Zhuk", "pinn_name": "Sofya Zhuk", "player": 49094}}, {"model": "tennis.alias", "pk": 286, "fields": {"dk_name": "Quentin Halys", "fd_name": "Quentin Halys", "pinn_name": "Quentin Halys", "player": 11445}}, {"model": "tennis.alias", "pk": 287, "fields": {"dk_name": "Jessika Ponchet", "fd_name": "Jessika Ponchet", "pinn_name": "Jessika Ponchet", "player": 41995}}, {"model": "tennis.alias", "pk": 288, "fields": {"dk_name": "Lloyd Harris", "fd_name": "Lloyd Harris", "pinn_name": "Lloyd Harris", "player": 70141}}, {"model": "tennis.alias", "pk": 289, "fields": {"dk_name": "Pedro Martinez", "fd_name": "Pedro Martinez", "pinn_name": "Pedro Martinez Portero", "player": 28756}}, {"model": "tennis.alias", "pk": 290, "fields": {"dk_name": "Rudolf Molleker", "fd_name": "Rudolf Molleker", "pinn_name": "Rudolf Molleker", "player": 71710}}, {"model": "tennis.alias", "pk": 291, "fields": {"dk_name": "Vera Zvonareva", "fd_name": "Vera Zvonareva", "pinn_name": "Vera Zvonareva", "player": 22087}}, {"model": "tennis.alias", "pk": 292, "fields": {"dk_name": "Kurumi Nara", "fd_name": "Kurumi Nara", "pinn_name": "Kurumi Nara", "player": 22620}}, {"model": "tennis.alias", "pk": 293, "fields": {"dk_name": "Antoine Hoang", "fd_name": "Antoine Hoang", "pinn_name": "Antoine Hoang", "player": 32894}}, {"model": "tennis.alias", "pk": 294, "fields": {"dk_name": "Gregoire Barrere", "fd_name": "Gregoire Barrere", "pinn_name": "Gregoire Barrere", "player": 6282}}, {"model": "tennis.alias", "pk": 295, "fields": {"dk_name": "Iga Swiatek", "fd_name": "Iga Swiatek", "pinn_name": "Iga Swiatek", "player": 52064}}, {"model": "tennis.alias", "pk": 296, "fields": {"dk_name": "Stefano Travaglia", "fd_name": "Stefano Travaglia", "pinn_name": "Stefano Travaglia", "player": 5868}}, {"model": "tennis.alias", "pk": 297, "fields": {"dk_name": "Martin Klizan", "fd_name": "Martin Klizan", "pinn_name": "Martin Klizan", "player": 5364}}, {"model": "tennis.alias", "pk": 298, "fields": {"dk_name": "Elena Rybakina", "fd_name": "Elena Rybakina", "pinn_name": "Elena Rybakina", "player": 49333}}, {"model": "tennis.alias", "pk": 299, "fields": {"dk_name": "Priscilla Hon", "fd_name": "Priscilla Hon", "pinn_name": "Priscilla Hon", "player": 43127}}, {"model": "tennis.alias", "pk": 300, "fields": {"dk_name": "Simone Bolelli", "fd_name": "Simone Bolelli", "pinn_name": "Simone Bolelli", "player": 4619}}, {"model": "tennis.alias", "pk": 301, "fields": {"dk_name": "Anna Tatishvili", "fd_name": "Anna Tatishvili", "pinn_name": "Anna Tatishvili", "player": 22603}}, {"model": "tennis.alias", "pk": 302, "fields": {"dk_name": "Selena Janicijevic", "fd_name": "Selena Janicijevic", "pinn_name": "Selena Janicijevic", "player": 63145}}, {"model": "tennis.alias", "pk": 303, "fields": {"dk_name": "Cedrik-Marcel Stebe", "fd_name": "Cedrik-Marcel Stebe", "pinn_name": "Cedrik-Marcel Stebe", "player": null}}, {"model": "tennis.alias", "pk": 304, "fields": {"dk_name": "Corentin Moutet", "fd_name": "Corentin Moutet", "pinn_name": "Corentin Moutet", "player": 70428}}, {"model": "tennis.alias", "pk": 305, "fields": {"dk_name": "Nicolas Mahut", "fd_name": "Nicolas Mahut", "pinn_name": "Nicolas Mahut", "player": 3917}}, {"model": "tennis.alias", "pk": 306, "fields": {"dk_name": "Chloe Paquet", "fd_name": "Chloe Paquet", "pinn_name": "Chloe Paquet", "player": 26557}}, {"model": "tennis.alias", "pk": 307, "fields": {"dk_name": "Magdalena Frech", "fd_name": "Magdalena Frech", "pinn_name": "Magdalena Frech", "player": 42729}}, {"model": "tennis.alias", "pk": 308, "fields": {"dk_name": "Katie Swan", "fd_name": "Katie Swan", "pinn_name": "Katie Swan", "player": 49455}}, {"model": "tennis.alias", "pk": 309, "fields": {"dk_name": "Heather Watson", "fd_name": "Heather Watson", "pinn_name": "Heather Watson", "player": 22599}}, {"model": "tennis.alias", "pk": 310, "fields": {"dk_name": "Ellen Perez", "fd_name": "Ellen Perez", "pinn_name": "Ellen Perez", "player": 32168}}, {"model": "tennis.alias", "pk": 311, "fields": {"dk_name": "Matthew Ebden", "fd_name": "Matthew Ebden", "pinn_name": "Matthew Ebden", "player": 5044}}, {"model": "tennis.alias", "pk": 312, "fields": {"dk_name": "Paula Badosa", "fd_name": "Paula Badosa Gibert", "pinn_name": "Paula Badosa Gibert", "player": 42663}}, {"model": "tennis.alias", "pk": 313, "fields": {"dk_name": "Maia Lumsden", "fd_name": "Maia Lumsden", "pinn_name": "Maia Lumsden", "player": 43141}}, {"model": "tennis.alias", "pk": 314, "fields": {"dk_name": "Dustin Brown", "fd_name": "Dustin Brown", "pinn_name": "Dustin Brown", "player": 4459}}, {"model": "tennis.alias", "pk": 315, "fields": {"dk_name": "James Ward", "fd_name": "James Ward", "pinn_name": "James Ward", "player": 4865}}, {"model": "tennis.alias", "pk": 316, "fields": {"dk_name": "Juan Martin Del Potro", "fd_name": "Juan Martin Del Potro", "pinn_name": "Juan Martin Del Potro", "player": null}}, {"model": "tennis.alias", "pk": 317, "fields": {"dk_name": "Maria Sharapova", "fd_name": "Maria Sharapova", "pinn_name": "Maria Sharapova", "player": 22116}}, {"model": "tennis.alias", "pk": 318, "fields": {"dk_name": "Mats Moraing", "fd_name": "Mats Moraing", "pinn_name": "Mats Moraing", "player": 23611}}, {"model": "tennis.alias", "pk": 319, "fields": {"dk_name": "Cem Ilkel", "fd_name": "Cem Ilkel", "pinn_name": "Cem Ilkel", "player": 17341}}, {"model": "tennis.alias", "pk": 320, "fields": {"dk_name": "Ons Jabeur", "fd_name": "Ons Jabeur", "pinn_name": "Ons Jabeur", "player": 24348}}, {"model": "tennis.alias", "pk": 321, "fields": {"dk_name": "Jay Clarke", "fd_name": "Jay Clarke", "pinn_name": "Jay Clarke", "player": 33892}}, {"model": "tennis.alias", "pk": 322, "fields": {"dk_name": "Dennis Novak", "fd_name": "Dennis Novak", "pinn_name": "Dennis Novak", "player": 10588}}, {"model": "tennis.alias", "pk": 323, "fields": {"dk_name": "Dominik Koepfer", "fd_name": "Dominik Koepfer", "pinn_name": "Dominik Koepfer", "player": 53491}}, {"model": "tennis.alias", "pk": 324, "fields": {"dk_name": "Kaja Juvan", "fd_name": "Kaja Juvan", "pinn_name": "Kaja Juvan", "player": 49807}}, {"model": "tennis.alias", "pk": 325, "fields": {"dk_name": "Tereza Martincova", "fd_name": "Tereza Martincova", "pinn_name": "Tereza Martincova", "player": 31631}}, {"model": "tennis.alias", "pk": 326, "fields": {"dk_name": "Yasutaka Uchiyama", "fd_name": "Yasutaka Uchiyama", "pinn_name": "Yasutaka Uchiyama", "player": 6020}}, {"model": "tennis.alias", "pk": 327, "fields": {"dk_name": "Paul Jubb", "fd_name": "Paul Jubb", "pinn_name": "Paul Jubb", "player": 84161}}, {"model": "tennis.alias", "pk": 328, "fields": {"dk_name": "Vitalia Diatchenko", "fd_name": "Vitalia Diatchenko", "pinn_name": "Vitalia Diatchenko", "player": 22536}}, {"model": "tennis.alias", "pk": 329, "fields": {"dk_name": "Lesley Kerkhove", "fd_name": "Lesley Kerkhove", "pinn_name": "Lesley Kerkhove", "player": 27868}}, {"model": "tennis.alias", "pk": 330, "fields": {"dk_name": "Jil Teichmann", "fd_name": "Jil Teichmann", "pinn_name": "Jil Teichmann", "player": 46423}}, {"model": "tennis.alias", "pk": 331, "fields": {"dk_name": "Giulia Gatto-Monticone", "fd_name": "Giulia Gatto-Monticone", "pinn_name": "Giulia Gatto-Monticone", "player": null}}, {"model": "tennis.alias", "pk": 332, "fields": {"dk_name": "Valentyna Ivakhnenko", "fd_name": "Valentyna Ivakhnenko", "pinn_name": "Valentyna Ivakhnenko", "player": 24403}}, {"model": "tennis.alias", "pk": 333, "fields": {"dk_name": "Irina Maria Bara", "fd_name": "Irina Maria Bara", "pinn_name": "Irina Maria Bara", "player": null}}, {"model": "tennis.alias", "pk": 334, "fields": {"dk_name": "Paula Ormaechea", "fd_name": "Paula Ormaechea", "pinn_name": "Paula Ormaechea", "player": 24308}}, {"model": "tennis.alias", "pk": 335, "fields": {"dk_name": "Gian Marco Moroni", "fd_name": "Gian Marco Moroni", "pinn_name": "Gian Marco Moroni", "player": null}}, {"model": "tennis.alias", "pk": 336, "fields": {"dk_name": "Arantxa Rus", "fd_name": "Arantxa Rus", "pinn_name": "Arantxa Rus", "player": 22531}}, {"model": "tennis.alias", "pk": 337, "fields": {"dk_name": "Fanny Stollar", "fd_name": "Fanny Stollar", "pinn_name": "Fanny Stollar", "player": 48448}}, {"model": "tennis.alias", "pk": 338, "fields": {"dk_name": "Kevin King", "fd_name": "Kevin King", "pinn_name": "Kevin King", "player": 10522}}, {"model": "tennis.alias", "pk": 339, "fields": {"dk_name": "Hailey Baptiste", "fd_name": "Hailey Baptiste", "pinn_name": "Hailey Baptiste", "player": 61378}}, {"model": "tennis.alias", "pk": 340, "fields": {"dk_name": "Marc Polmans", "fd_name": "Marc Polmans", "pinn_name": "Marc Polmans", "player": 17345}}, {"model": "tennis.alias", "pk": 341, "fields": {"dk_name": "Anna Kalinskaya", "fd_name": "Anna Kalinskaya", "pinn_name": "Anna Kalinskaya", "player": 49248}}, {"model": "tennis.alias", "pk": 342, "fields": {"dk_name": "Coco Vandeweghe", "fd_name": "Coco Vandeweghe", "pinn_name": "Coco Vandeweghe", "player": 22497}}, {"model": "tennis.alias", "pk": 343, "fields": {"dk_name": "Tommy Paul", "fd_name": "Tommy Paul", "pinn_name": "Tommy Paul", "player": 32991}}, {"model": "tennis.alias", "pk": 344, "fields": {"dk_name": "Mayo Hibi", "fd_name": "Mayo Hibi", "pinn_name": "Mayo Hibi", "player": 32084}}, {"model": "tennis.alias", "pk": 345, "fields": {"dk_name": "Tim Smyczek", "fd_name": "Tim Smyczek", "pinn_name": "Tim Smyczek", "player": 5058}}, {"model": "tennis.alias", "pk": 346, "fields": {"dk_name": "Sebastian Ofner", "fd_name": "Sebastian Ofner", "pinn_name": "Sebastian Ofner", "player": 28830}}, {"model": "tennis.alias", "pk": 347, "fields": {"dk_name": "Danielle Collins", "fd_name": "Danielle Collins", "pinn_name": "Danielle Collins", "player": 26202}}, {"model": "tennis.alias", "pk": 348, "fields": {"dk_name": "Catherine Bellis", "fd_name": "Catherine Bellis", "pinn_name": "Catherine Bellis", "player": null}}, {"model": "tennis.alias", "pk": 349, "fields": {"dk_name": "Liudmila Samsonova", "fd_name": "Liudmila Samsonova", "pinn_name": "Ludmilla Samsonova", "player": 48652}}, {"model": "tennis.alias", "pk": 350, "fields": {"dk_name": "Soonwoo Kwon", "fd_name": "Soonwoo Kwon", "pinn_name": "Soonwoo Kwon", "player": 34495}}, {"model": "tennis.alias", "pk": 351, "fields": {"dk_name": "Christopher O'connell", "fd_name": "Christopher O'connell", "pinn_name": "Christopher O'Connell", "player": null}}, {"model": "tennis.alias", "pk": 352, "fields": {"dk_name": "Yen-Hsun Lu", "fd_name": "Yen-Hsun Lu", "pinn_name": "Yen-Hsun Lu", "player": null}}, {"model": "tennis.alias", "pk": 353, "fields": {"dk_name": "Danilo Petrovic", "fd_name": "Danilo Petrovic", "pinn_name": "Danilo Petrovic", "player": 5891}}, {"model": "tennis.alias", "pk": 354, "fields": {"dk_name": "Facundo Bagnis", "fd_name": "Facundo Bagnis", "pinn_name": "Facundo Bagnis", "player": 5476}}, {"model": "tennis.alias", "pk": 355, "fields": {"dk_name": "Jozef Kovalik", "fd_name": "Jozef Kovalik", "pinn_name": "Jozef Kovalik", "player": 6061}}, {"model": "tennis.alias", "pk": 356, "fields": {"dk_name": "Brayden Schnur", "fd_name": "Brayden Schnur", "pinn_name": "Brayden Schnur", "player": 11775}}, {"model": "tennis.alias", "pk": 357, "fields": {"dk_name": "Francisco Cerundolo", "fd_name": "Francisco Cerundolo", "pinn_name": "Francisco Cerundolo", "player": 74942}}, {"model": "tennis.alias", "pk": 358, "fields": {"dk_name": "Go Soeda", "fd_name": "Go Soeda", "pinn_name": "Go Soeda", "player": 4423}}, {"model": "tennis.alias", "pk": 359, "fields": {"dk_name": "Filip Horansky", "fd_name": "Filip Horansky", "pinn_name": "Filip Horansky", "player": 6096}}, {"model": "tennis.alias", "pk": 360, "fields": {"dk_name": "Tallon Griekspoor", "fd_name": "Tallon Griekspoor", "pinn_name": "Tallon Griekspoor", "player": 50344}}, {"model": "tennis.alias", "pk": 361, "fields": {"dk_name": "Facundo Diaz Acosta", "fd_name": "Facundo Diaz Acosta", "pinn_name": "Facundo Diaz Acosta", "player": 86113}}, {"model": "tennis.alias", "pk": 362, "fields": {"dk_name": "Brian Shi", "fd_name": "Brian Shi", "pinn_name": "Brian Shi", "player": 86968}}, {"model": "tennis.alias", "pk": 363, "fields": {"dk_name": "Thiago Monteiro", "fd_name": "Thiago Monteiro", "pinn_name": "Thiago Monteiro", "player": 6315}}, {"model": "tennis.alias", "pk": 364, "fields": {"dk_name": "Vasek Pospisil", "fd_name": "Vasek Pospisil", "pinn_name": "Vasek Pospisil", "player": 5565}}, {"model": "tennis.alias", "pk": 365, "fields": {"dk_name": "Joao Domingues", "fd_name": "Joao Domingues", "pinn_name": "Joao Domingues", "player": 6235}}, {"model": "tennis.alias", "pk": 366, "fields": {"dk_name": "Jason Jung", "fd_name": "Jason Jung", "pinn_name": "Jason Jung", "player": 5351}}, {"model": "tennis.alias", "pk": 367, "fields": {"dk_name": "Brandon Nakashima", "fd_name": "Brandon Nakashima", "pinn_name": "Brandon Nakashima", "player": 84576}}, {"model": "tennis.alias", "pk": 368, "fields": {"dk_name": "Attila Balazs", "fd_name": "Attila Balazs", "pinn_name": "Attila Balazs", "player": 5219}}, {"model": "tennis.alias", "pk": 369, "fields": {"dk_name": "Mikael Ymer", "fd_name": "Mikael Ymer", "pinn_name": "Mikael Ymer", "player": 70056}}, {"model": "tennis.alias", "pk": 370, "fields": {"dk_name": "Gianluca Mager", "fd_name": "Gianluca Mager", "pinn_name": "Gianluca Mager", "player": 32879}}, {"model": "tennis.alias", "pk": 371, "fields": {"dk_name": "Egor Gerasimov", "fd_name": "Egor Gerasimov", "pinn_name": "Egor Gerasimov", "player": 6064}}, {"model": "tennis.alias", "pk": 372, "fields": {"dk_name": "Jack Sock", "fd_name": "Jack Sock", "pinn_name": "Jack Sock", "player": 6044}}, {"model": "tennis.alias", "pk": 373, "fields": {"dk_name": "Federico Coria", "fd_name": "Federico Coria", "pinn_name": "Federico Coria", "player": 5934}}, {"model": "tennis.alias", "pk": 374, "fields": {"dk_name": "Marie Bouzkova", "fd_name": "Marie Bouzkova", "pinn_name": "Marie Bouzkova", "player": 46636}}, {"model": "tennis.alias", "pk": 375, "fields": {"dk_name": "Carlos Taberner", "fd_name": "Carlos Taberner", "pinn_name": "Carlos Taberner", "player": 33657}}, {"model": "tennis.alias", "pk": 376, "fields": {"dk_name": "Anastasia Potapova", "fd_name": "Anastasia Potapova", "pinn_name": "Anastasia Potapova", "player": 50795}}, {"model": "tennis.alias", "pk": 377, "fields": {"dk_name": "Tomas Barrios Vera", "fd_name": "Marcelo Tomas Barrios Vera", "pinn_name": "Marcelo Tomas Barrios-Vera", "player": 69927}}, {"model": "tennis.alias", "pk": 378, "fields": {"dk_name": "Gerardo Lopez Villasenor", "fd_name": "Gerardo Lopez Villasenor", "pinn_name": "Gerardo Lopez Villasenor", "player": 32989}}, {"model": "tennis.alias", "pk": 379, "fields": {"dk_name": "Kateryna Bondarenko", "fd_name": "Kateryna Bondarenko", "pinn_name": "Kateryna Bondarenko", "player": 22301}}, {"model": "tennis.alias", "pk": 380, "fields": {"dk_name": "Danka Kovinic", "fd_name": "Danka Kovinic", "pinn_name": "Danka Kovinic", "player": 26580}}, {"model": "tennis.alias", "pk": 381, "fields": {"dk_name": "Bethanie Mattek-Sands", "fd_name": "Bethanie Mattek-Sands", "pinn_name": "Bethanie Mattek Sands", "player": 22066}}, {"model": "tennis.alias", "pk": 382, "fields": {"dk_name": "Leylah Annie Fernandez", "fd_name": "Leylah Annie Fernandez", "pinn_name": "Leylah Annie Fernandez", "player": 60094}}, {"model": "tennis.alias", "pk": 383, "fields": {"dk_name": "Leonie Kung", "fd_name": "Leonie Kung", "pinn_name": "Leonie Kung", "player": 49887}}, {"model": "tennis.alias", "pk": 384, "fields": {"dk_name": "Barbora Krejcikova", "fd_name": "Barbora Krejcikova", "pinn_name": "Barbora Krejcikova", "player": 31888}}, {"model": "tennis.alias", "pk": 385, "fields": {"dk_name": "Cori Gauff", "fd_name": "Cori Gauff", "pinn_name": "Cori Gauff", "player": 61536}}, {"model": "tennis.alias", "pk": 386, "fields": {"dk_name": "Andy Murray", "fd_name": "Andy Murray", "pinn_name": "Andy Murray", "player": 4913}}, {"model": "tennis.alias", "pk": 387, "fields": {"dk_name": "Ann Li", "fd_name": "Ann Li", "pinn_name": "Ann Li", "player": 51337}}, {"model": "tennis.alias", "pk": 388, "fields": {"dk_name": "Salvatore Caruso", "fd_name": "Salvatore Caruso", "pinn_name": "Salvatore Caruso", "player": 6085}}, {"model": "tennis.alias", "pk": 389, "fields": {"dk_name": "Mitchell Krueger", "fd_name": "Mitchell Krueger", "pinn_name": "Mitchell Krueger", "player": 6269}}, {"model": "tennis.alias", "pk": 390, "fields": {"dk_name": "Caroline Dolehide", "fd_name": "Caroline Dolehide", "pinn_name": "Caroline Dolehide", "player": 48271}}, {"model": "tennis.alias", "pk": 391, "fields": {"dk_name": "Maxime Cressy", "fd_name": "Maxime Cressy", "pinn_name": "Maxime Cressy", "player": 75125}}, {"model": "tennis.alias", "pk": 392, "fields": {"dk_name": "Varvara Gracheva", "fd_name": "Varvara Gracheva", "pinn_name": "Varvara Gracheva", "player": 59113}}, {"model": "tennis.alias", "pk": 394, "fields": {"dk_name": "Usue Maitane Arconada", "fd_name": "Usue Maitane Arconada", "pinn_name": "Usue Maitane Arconada", "player": null}}, {"model": "tennis.alias", "pk": 395, "fields": {"dk_name": "Lizette Cabrera", "fd_name": "Lizette Cabrera", "pinn_name": "Lizette Cabrera", "player": 43123}}, {"model": "tennis.alias", "pk": 396, "fields": {"dk_name": "Evgeny Donskoy", "fd_name": "Evgeny Donskoy", "pinn_name": "Evgeny Donskoy", "player": 5528}}, {"model": "tennis.alias", "pk": 397, "fields": {"dk_name": "Alejandro Davidovich Fokina", "fd_name": "Alejandro Davidovich Fokina", "pinn_name": "Alejandro Davidovich Fokina", "player": 71182}}, {"model": "tennis.alias", "pk": 398, "fields": {"dk_name": "Thai-Son Kwiatkowski", "fd_name": "Thai-Son Kwiatkowski", "pinn_name": "Thai-Son Kwiatkowski", "player": null}}, {"model": "tennis.alias", "pk": 399, "fields": {"dk_name": "Maddison Inglis", "fd_name": "Maddison Inglis", "pinn_name": "Maddison Inglis", "player": 46706}}, {"model": "tennis.alias", "pk": 400, "fields": {"dk_name": "Sebastian Korda", "fd_name": "Sebastian Korda", "pinn_name": "Sebastian Korda", "player": 71992}}, {"model": "tennis.alias", "pk": 401, "fields": {"dk_name": "Mohamed Safwat", "fd_name": "Mohamed Safwat", "pinn_name": "Mohamed Safwat", "player": 5621}}, {"model": "tennis.alias", "pk": 402, "fields": {"dk_name": "Anhelina Kalinina", "fd_name": "Anhelina Kalinina", "pinn_name": "Anhelina Kalinina", "player": 43054}}, {"model": "tennis.alias", "pk": 403, "fields": {"dk_name": "Feliciano Lopez", "fd_name": "Feliciano Lopez", "pinn_name": "Feliciano Lopez", "player": 3852}}, {"model": "tennis.alias", "pk": 404, "fields": {"dk_name": "Kamil Majchrzak", "fd_name": "Kamil Majchrzak", "pinn_name": "Kamil Majchrzak", "player": 11779}}, {"model": "tennis.alias", "pk": 405, "fields": {"dk_name": "Norbert Gombos", "fd_name": "Norbert Gombos", "pinn_name": "Norbert Gombos", "player": 5601}}, {"model": "tennis.alias", "pk": 407, "fields": {"dk_name": "Jeffrey John Wolf", "fd_name": "Jeffrey John Wolf", "pinn_name": "Jeffrey John Wolf", "player": null}}, {"model": "tennis.alias", "pk": 408, "fields": {"dk_name": "Emil Ruusuvuori", "fd_name": "Emil Ruusuvuori", "pinn_name": "Emil Ruusuvuori", "player": 71391}}, {"model": "tennis.alias", "pk": 409, "fields": {"dk_name": "Jannik Sinner", "fd_name": "Jannik Sinner", "pinn_name": "Jannik Sinner", "player": 83101}}, {"model": "tennis.alias", "pk": 410, "fields": {"dk_name": "Claire Liu", "fd_name": "Claire Liu", "pinn_name": "Claire Liu", "player": 49181}}, {"model": "tennis.alias", "pk": 411, "fields": {"dk_name": "Katrina Scott", "fd_name": "Katrina Scott", "pinn_name": "Katrina Scott", "player": 62351}}, {"model": "tennis.alias", "pk": 412, "fields": {"dk_name": "Sumit Nagal", "fd_name": "Sumit Nagal", "pinn_name": "Sumit Nagal", "player": 11561}}, {"model": "tennis.alias", "pk": 413, "fields": {"dk_name": "Andrey Kuznetsov", "fd_name": "Andrey Kuznetsov", "pinn_name": "Andrey Kuznetsov", "player": 5709}}, {"model": "tennis.alias", "pk": 414, "fields": {"dk_name": "Viktoriya Tomova", "fd_name": "Viktoriya Tomova", "pinn_name": "Viktoriya Tomova", "player": 24624}}, {"model": "tennis.alias", "pk": 415, "fields": {"dk_name": "Yanina Wickmayer", "fd_name": "Yanina Wickmayer", "pinn_name": "Yanina Wickmayer", "player": 22466}}, {"model": "tennis.alias", "pk": 416, "fields": {"dk_name": "Tsvetana Pironkova", "fd_name": "Tsvetana Pironkova", "pinn_name": "Tsvetana Pironkova", "player": 22331}}, {"model": "tennis.alias", "pk": 417, "fields": {"dk_name": "Kristie Ahn", "fd_name": "Kristie Ahn", "pinn_name": "Kristie Ahn", "player": 22486}}, {"model": "tennis.alias", "pk": 418, "fields": {"dk_name": "Barbara Haas", "fd_name": "Barbara Haas", "pinn_name": "Barbara Haas", "player": 24391}}, {"model": "tennis.alias", "pk": 419, "fields": {"dk_name": "Katarzyna Kawa", "fd_name": "Katarzyna Kawa", "pinn_name": "Katarzyna Kawa", "player": 26454}}, {"model": "tennis.alias", "pk": 420, "fields": {"dk_name": "Michael Mmoh", "fd_name": "Michael Mmoh", "pinn_name": "Michael Mmoh", "player": 11566}}, {"model": "tennis.alias", "pk": 421, "fields": {"dk_name": "Ernesto Escobedo", "fd_name": "Ernesto Escobedo", "pinn_name": "Ernesto Escobedo", "player": 28624}}, {"model": "tennis.alias", "pk": 422, "fields": {"dk_name": "Olga Govortsova", "fd_name": "Olga Govortsova", "pinn_name": "Olga Govortsova", "player": 22433}}, {"model": "tennis.alias", "pk": 423, "fields": {"dk_name": "Patricia Maria Tig", "fd_name": "Patricia Maria Tig", "pinn_name": "Patricia Maria Tig", "player": null}}, {"model": "tennis.alias", "pk": 424, "fields": {"dk_name": "Marc-Andrea Huesler", "fd_name": "Marc-Andrea Huesler", "pinn_name": "Marc Andrea Huesler", "player": null}}, {"model": "tennis.alias", "pk": 425, "fields": {"dk_name": "Lorenzo Musetti", "fd_name": "Lorenzo Musetti", "pinn_name": "Lorenzo Musetti", "player": 85789}}, {"model": "tennis.alias", "pk": 426, "fields": {"dk_name": "Yannick Hanfmann", "fd_name": "Yannick Hanfmann", "pinn_name": "Yannick Hanfmann", "player": 5856}}, {"model": "tennis.alias", "pk": 427, "fields": {"dk_name": "Clara Burel", "fd_name": "Clara Burel", "pinn_name": "Clara Burel", "player": 51898}}, {"model": "tennis.alias", "pk": 428, "fields": {"dk_name": "Nadia Podoroska", "fd_name": "Nadia Podoroska", "pinn_name": "Nadia Podoroska", "player": 32201}}, {"model": "tennis.alias", "pk": 429, "fields": {"dk_name": "Jurij Rodionov", "fd_name": "Jurij Rodionov", "pinn_name": "Jurij Rodionov", "player": 71771}}, {"model": "tennis.alias", "pk": 430, "fields": {"dk_name": "Tomas Machac", "fd_name": "Tomas Machac", "pinn_name": "Tomas Machac", "player": 86412}}, {"model": "tennis.alias", "pk": 431, "fields": {"dk_name": "Elliot Benchetrit", "fd_name": "Elliot Benchetrit", "pinn_name": "Elliot Benchetrit", "player": 71965}}, {"model": "tennis.alias", "pk": 432, "fields": {"dk_name": "Lorenzo Giustino", "fd_name": "Lorenzo Giustino", "pinn_name": "Lorenzo Giustino", "player": 5827}}, {"model": "tennis.alias", "pk": 433, "fields": {"dk_name": "Steven Diez", "fd_name": "Steven Diez", "pinn_name": "Steven Diez", "player": 5717}}, {"model": "tennis.alias", "pk": 434, "fields": {"dk_name": "Daniel Altmaier", "fd_name": "Daniel Altmaier", "pinn_name": "Daniel Altmaier", "player": 34905}}, {"model": "tennis.alias", "pk": 435, "fields": {"dk_name": "Liam Broady", "fd_name": "Liam Broady", "pinn_name": "Liam Broady", "player": 6267}}, {"model": "tennis.alias", "pk": 436, "fields": {"dk_name": "Arthur Rinderknech", "fd_name": "Arthur Rinderknech", "pinn_name": "Arthur Rinderknech", "player": 33060}}, {"model": "tennis.alias", "pk": 437, "fields": {"dk_name": "James Duckworth", "fd_name": "James Duckworth", "pinn_name": "James Duckworth", "player": 5888}}, {"model": "tennis.alias", "pk": 438, "fields": {"dk_name": "Emilio Gomez", "fd_name": "Emilio Gomez", "pinn_name": "Emilio Gomez", "player": 5863}}, {"model": "tennis.alias", "pk": 439, "fields": {"dk_name": "Elsa Jacquemot", "fd_name": "Elsa Jacquemot", "pinn_name": "Elsa Jacquemot", "player": 61408}}, {"model": "tennis.alias", "pk": 440, "fields": {"dk_name": "Tamara Korpatsch", "fd_name": "Tamara Korpatsch", "pinn_name": "Tamara Korpatsch", "player": 42037}}, {"model": "tennis.alias", "pk": 441, "fields": {"dk_name": "Diane Parry", "fd_name": "Diane Parry", "pinn_name": "Diane Parry", "player": 60056}}, {"model": "tennis.alias", "pk": 442, "fields": {"dk_name": "Nikola Milojevic", "fd_name": "Nikola Milojevic", "pinn_name": "Nikola Milojevic", "player": 10734}}, {"model": "tennis.alias", "pk": 443, "fields": {"dk_name": "Yuichi Sugita", "fd_name": "Yuichi Sugita", "pinn_name": "Yuichi Sugita", "player": 5209}}, {"model": "tennis.alias", "pk": 444, "fields": {"dk_name": "Andrej Martin", "fd_name": "Andrej Martin", "pinn_name": "Andrej Martin", "player": 5403}}, {"model": "tennis.alias", "pk": 445, "fields": {"dk_name": "Harmony Tan", "fd_name": "Harmony Tan", "pinn_name": "Harmony Tan", "player": 42468}}, {"model": "tennis.alias", "pk": 446, "fields": {"dk_name": "Kamilla Rakhimova", "fd_name": "Kamilla Rakhimova", "pinn_name": "Kamilla Rakhimova", "player": 51114}}, {"model": "tennis.alias", "pk": 447, "fields": {"dk_name": "Benjamin Bonzi", "fd_name": "Benjamin Bonzi", "pinn_name": "Benjamin Bonzi", "player": 32835}}, {"model": "tennis.alias", "pk": 448, "fields": {"dk_name": "Hugo Gaston", "fd_name": "Hugo Gaston", "pinn_name": "Hugo Gaston", "player": 71510}}, {"model": "tennis.alias", "pk": 449, "fields": {"dk_name": "Oscar Otte", "fd_name": "Oscar Otte", "pinn_name": "Oscar Otte", "player": 6200}}, {"model": "tennis.alias", "pk": 450, "fields": {"dk_name": "Roman Safiullin", "fd_name": "Roman Safiullin", "pinn_name": "Roman Safiullin", "player": 32837}}, {"model": "tennis.alias", "pk": 451, "fields": {"dk_name": "Mischa Zverev", "fd_name": "Mischa Zverev", "pinn_name": "Mischa Zverev", "player": 4994}}, {"model": "tennis.alias", "pk": 452, "fields": {"dk_name": "Pavel Kotov", "fd_name": "Pavel Kotov", "pinn_name": "Pavel Kotov", "player": 71347}}, {"model": "tennis.alias", "pk": 453, "fields": {"dk_name": "Nino Serdarusic", "fd_name": "Nino Serdarusic", "pinn_name": "Nino Serdarusic", "player": 32820}}, {"model": "tennis.alias", "pk": 454, "fields": {"dk_name": "Viktor Troicki", "fd_name": "Viktor Troicki", "pinn_name": "Viktor Troicki", "player": 4677}}, {"model": "tennis.alias", "pk": 455, "fields": {"dk_name": "Kimmer Coppejans", "fd_name": "Kimmer Coppejans", "pinn_name": "Kimmer Coppejans", "player": 6279}}, {"model": "tennis.alias", "pk": 456, "fields": {"dk_name": "Zizou Bergs", "fd_name": "Zizou Bergs", "pinn_name": "Zizou Bergs", "player": 71275}}, {"model": "tennis.alias", "pk": 457, "fields": {"dk_name": "Luca Nardi", "fd_name": "Luca Nardi", "pinn_name": "Luca Nardi", "player": 87020}}, {"model": "tennis.alias", "pk": 458, "fields": {"dk_name": "Aslan Karatsev", "fd_name": "Aslan Karatsev", "pinn_name": "Aslan Karatsev", "player": 6220}}, {"model": "tennis.alias", "pk": 459, "fields": {"dk_name": "Katarina Zavatska", "fd_name": "Katarina Zavatska", "pinn_name": "Katarina Zavatska", "player": 49947}}, {"model": "tennis.alias", "pk": 460, "fields": {"dk_name": "Dimitar Kuzmanov", "fd_name": "Dimitar Kuzmanov", "pinn_name": "Dimitar Kuzmanov", "player": 6206}}, {"model": "tennis.alias", "pk": 461, "fields": {"dk_name": "Illya Marchenko", "fd_name": "Illya Marchenko", "pinn_name": "Illya Marchenko", "player": 5006}}, {"model": "tennis.alias", "pk": 462, "fields": {"dk_name": "Jonas Forejtek", "fd_name": "Jonas Forejtek", "pinn_name": "Jonas Forejtek", "player": 86347}}, {"model": "tennis.alias", "pk": 463, "fields": {"dk_name": "Jana Fett", "fd_name": "Jana Fett", "pinn_name": "Jana Fett", "player": 46461}}, {"model": "tennis.alias", "pk": 464, "fields": {"dk_name": "Julia Grabher", "fd_name": "Julia Grabher", "pinn_name": "Julia Grabher", "player": 42994}}, {"model": "tennis.alias", "pk": 465, "fields": {"dk_name": "Oceane Dodin", "fd_name": "Oceane Dodin", "pinn_name": "Oceane Dodin", "player": 31822}}, {"model": "tennis.alias", "pk": 466, "fields": {"dk_name": "Ying-Ying Duan", "fd_name": "Ying-Ying Duan", "pinn_name": "Ying-Ying Duan", "player": null}}, {"model": "tennis.alias", "pk": 467, "fields": {"dk_name": "Paige Mary Hourigan", "fd_name": "Paige Mary Hourigan", "pinn_name": "Paige Mary Hourigan", "player": null}}, {"model": "tennis.alias", "pk": 468, "fields": {"dk_name": "Kacper Zuk", "fd_name": "Kacper Zuk", "pinn_name": "Kacper Zuk", "player": 71522}}, {"model": "tennis.alias", "pk": 469, "fields": {"dk_name": "Bianca Turati", "fd_name": "Bianca Turati", "pinn_name": "Bianca Turati", "player": 47222}}, {"model": "tennis.alias", "pk": 470, "fields": {"dk_name": "Anastasia Gasanova", "fd_name": "Anastasia Gasanova", "pinn_name": "Anastasia Gasanova", "player": 47730}}, {"model": "tennis.alias", "pk": 471, "fields": {"dk_name": "Yaroslava Shvedova", "fd_name": "Yaroslava Shvedova", "pinn_name": "Yaroslava Shvedova", "player": 22367}}, {"model": "tennis.alias", "pk": 472, "fields": {"dk_name": "Altug Celikbilek", "fd_name": "Altug Celikbilek", "pinn_name": "Altug Celikbilek", "player": 28185}}, {"model": "tennis.alias", "pk": 473, "fields": {"dk_name": "Andrea Arnaboldi", "fd_name": "Andrea Arnaboldi", "pinn_name": "Andrea Arnaboldi", "player": 5056}}, {"model": "tennis.alias", "pk": 474, "fields": {"dk_name": "Jodie Anna Burrage", "fd_name": "Jodie Anna Burrage", "pinn_name": "Jodie Anna Burrage", "player": null}}, {"model": "tennis.alias", "pk": 475, "fields": {"dk_name": "Amandine Hesse", "fd_name": "Amandine Hesse", "pinn_name": "Amandine Hesse", "player": 25984}}, {"model": "tennis.alias", "pk": 476, "fields": {"dk_name": "Zhaoxuan Yang", "fd_name": "Zhaoxuan Yang", "pinn_name": "Zhaoxuan Yang", "player": 31596}}, {"model": "tennis.alias", "pk": 477, "fields": {"dk_name": "Ulrikke Eikeri", "fd_name": "Ulrikke Eikeri", "pinn_name": "Ulrikke Eikeri", "player": 31218}}, {"model": "tennis.alias", "pk": 478, "fields": {"dk_name": "Kimberly Birrell", "fd_name": "Kimberly Birrell", "pinn_name": "Kimberly Birrell", "player": 47449}}, {"model": "tennis.alias", "pk": 479, "fields": {"dk_name": "Lin Zhu", "fd_name": "Lin Zhu", "pinn_name": "Lin Zhu", "player": 24789}}, {"model": "tennis.alias", "pk": 480, "fields": {"dk_name": "Valeria Savinykh", "fd_name": "Valeria Savinykh", "pinn_name": "Valeria Savinykh", "player": 24314}}, {"model": "tennis.alias", "pk": 481, "fields": {"dk_name": "Olivia Gadecki", "fd_name": "Olivia Gadecki", "pinn_name": "Olivia Gadecki", "player": 51904}}, {"model": "tennis.alias", "pk": 482, "fields": {"dk_name": "Thanasi Kokkinakis", "fd_name": "Thanasi Kokkinakis", "pinn_name": "Thanasi Kokkinakis", "player": 6409}}, {"model": "tennis.alias", "pk": 483, "fields": {"dk_name": "Li Tu", "fd_name": "Li Tu", "pinn_name": "Li Tu", "player": 11439}}, {"model": "tennis.alias", "pk": 484, "fields": {"dk_name": "Max Purcell", "fd_name": "Max Purcell", "pinn_name": "Max Purcell", "player": 34282}}, {"model": "tennis.alias", "pk": 485, "fields": {"dk_name": "Blake Mott", "fd_name": "Blake Mott", "pinn_name": "Blake Mott", "player": 6411}}, {"model": "tennis.alias", "pk": 486, "fields": {"dk_name": "Jason Kubler", "fd_name": "Jason Kubler", "pinn_name": "Jason Kubler", "player": 6172}}, {"model": "tennis.alias", "pk": 487, "fields": {"dk_name": "Botic Van De Zandschulp", "fd_name": "Botic Van De Zandschulp", "pinn_name": "Botic van de Zandschulp", "player": 25149}}, {"model": "tennis.alias", "pk": 488, "fields": {"dk_name": "Borna Gojo", "fd_name": "Borna Gojo", "pinn_name": "Borna Gojo", "player": 35270}}, {"model": "tennis.alias", "pk": 489, "fields": {"dk_name": "Mikael Torpegaard", "fd_name": "Mikael Torpegaard", "pinn_name": "Mikael Torpegaard", "player": 11438}}, {"model": "tennis.alias", "pk": 490, "fields": {"dk_name": "Mario Vilella Martinez", "fd_name": "Mario Vilella Martinez", "pinn_name": "Mario Vilella Martinez", "player": 6394}}, {"model": "tennis.alias", "pk": 491, "fields": {"dk_name": "Frederico Ferreira Silva", "fd_name": "Frederico Ferreira Silva", "pinn_name": "Frederico Ferreira Silva", "player": 6379}}, {"model": "tennis.alias", "pk": 492, "fields": {"dk_name": "Andrew Harris", "fd_name": "Andrew Harris", "pinn_name": "Andrew Harris", "player": 6288}}, {"model": "tennis.alias", "pk": 493, "fields": {"dk_name": "Tristan Schoolkate", "fd_name": "Tristan Schoolkate", "pinn_name": "Tristan Schoolkate", "player": 89280}}, {"model": "tennis.alias", "pk": 494, "fields": {"dk_name": "Alexandre Muller", "fd_name": "Alexandre Muller", "pinn_name": "Alexandre Muller", "player": 28970}}, {"model": "tennis.alias", "pk": 495, "fields": {"dk_name": "Carlos Alcaraz", "fd_name": "Carlos Alcaraz Garfia", "pinn_name": "Carlos Alcaraz Garfia", "player": 86729}}, {"model": "tennis.alias", "pk": 496, "fields": {"dk_name": "Georgina Garcia Perez", "fd_name": "Georgina Garcia Perez", "pinn_name": "Georgina Garcia Perez", "player": 25252}}, {"model": "tennis.alias", "pk": 497, "fields": {"dk_name": "Harry Bourchier", "fd_name": "Harry Bourchier", "pinn_name": "Harry Bourchier", "player": 17343}}, {"model": "tennis.alias", "pk": 498, "fields": {"dk_name": "Mayar Sherif", "fd_name": "Mayar Sherif", "pinn_name": "Mayar Sherif", "player": 41133}}, {"model": "tennis.alias", "pk": 499, "fields": {"dk_name": "Arina Rodionova", "fd_name": "Arina Rodionova", "pinn_name": "Arina Rodionova", "player": 22651}}, {"model": "tennis.alias", "pk": 500, "fields": {"dk_name": "Aleksandar Vukic", "fd_name": "Aleksandar Vukic", "pinn_name": "Aleksandar Vukic", "player": 34284}}, {"model": "tennis.alias", "pk": 501, "fields": {"dk_name": "Christopher Eubanks", "fd_name": "Christopher Eubanks", "pinn_name": "Christopher Eubanks", "player": 11139}}, {"model": "tennis.alias", "pk": 502, "fields": {"dk_name": "Adrian Andreev", "fd_name": "Adrian Andreev", "pinn_name": "Adrian Andreev", "player": 74915}}, {"model": "tennis.alias", "pk": 503, "fields": {"dk_name": "Nicolas Kicker", "fd_name": "Nicolas Kicker", "pinn_name": "Nicolas Kicker", "player": 6030}}, {"model": "tennis.alias", "pk": 504, "fields": {"dk_name": "Tomas Martin Etcheverry", "fd_name": "Tomas Martin Etcheverry", "pinn_name": "Tomas Martin Etcheverry", "player": 70376}}, {"model": "tennis.alias", "pk": 505, "fields": {"dk_name": "Joao Menezes", "fd_name": "Joao Menezes", "pinn_name": "Joao Menezes", "player": 10764}}, {"model": "tennis.alias", "pk": 506, "fields": {"dk_name": "Juan Manuel Cerundolo", "fd_name": "Juan Manuel Cerundolo", "pinn_name": "Juan Manuel Cerundolo", "player": 86108}}, {"model": "tennis.alias", "pk": 507, "fields": {"dk_name": "Storm Sanders", "fd_name": "Storm Sanders", "pinn_name": "Storm Sanders", "player": 28200}}, {"model": "tennis.alias", "pk": 508, "fields": {"dk_name": "Roberto Marcora", "fd_name": "Roberto Marcora", "pinn_name": "Roberto Marcora", "player": 5396}}, {"model": "tennis.alias", "pk": 509, "fields": {"dk_name": "Thiago Agustin Tirante", "fd_name": "Thiago Agustin Tirante", "pinn_name": "Thiago Agustin Tirante", "player": null}}, {"model": "tennis.alias", "pk": 510, "fields": {"dk_name": "Clara Tauson", "fd_name": "Clara Tauson", "pinn_name": "Clara Tauson", "player": 60745}}, {"model": "tennis.alias", "pk": 511, "fields": {"dk_name": "Lukas Klein", "fd_name": "Lukas Klein", "pinn_name": "Lukas Klein", "player": 36110}}, {"model": "tennis.alias", "pk": 512, "fields": {"dk_name": "Holger Vitus Nodskov Rune", "fd_name": "Holger Vitus Nodskov Rune", "pinn_name": "Holger Vitus Nodskov Rune", "player": null}}, {"model": "tennis.alias", "pk": 514, "fields": {"dk_name": "Ana Konjuh", "fd_name": "Ana Konjuh", "pinn_name": "Ana Konjuh", "player": 43270}}, {"model": "tennis.alias", "pk": 515, "fields": {"dk_name": "Blaz Rola", "fd_name": "Blaz Rola", "pinn_name": "Blaz Rola", "player": 5629}}, {"model": "tennis.alias", "pk": 516, "fields": {"dk_name": "Ramkumar Ramanathan", "fd_name": "Ramkumar Ramanathan", "pinn_name": "Ramkumar Ramanathan", "player": 6354}}, {"model": "tennis.alias", "pk": 517, "fields": {"dk_name": "Sebastian Baez", "fd_name": "Sebastian Baez", "pinn_name": "Sebastian Baez", "player": 74944}}, {"model": "tennis.alias", "pk": 518, "fields": {"dk_name": "Alejandro Tabilo", "fd_name": "Alejandro Tabilo", "pinn_name": "Alejandro Tabilo", "player": 33010}}, {"model": "tennis.alias", "pk": 519, "fields": {"dk_name": "Juan Pablo Varillas", "fd_name": "Juan Pablo Varillas", "pinn_name": "Juan Pablo Varillas", "player": null}}, {"model": "tennis.alias", "pk": 520, "fields": {"dk_name": "Alex Molcan", "fd_name": "Alex Molcan", "pinn_name": "Alex Molcan", "player": 70010}}, {"model": "tennis.alias", "pk": 521, "fields": {"dk_name": "Petros Tsitsipas", "fd_name": "Petros Tsitsipas", "pinn_name": "Petros Tsitsipas", "player": 74865}}, {"model": "tennis.alias", "pk": 522, "fields": {"dk_name": "Bernabe Zapata Miralles", "fd_name": "Bernabe Zapata Miralles", "pinn_name": "Bernabe Zapata Miralles", "player": 33632}}, {"model": "tennis.alias", "pk": 523, "fields": {"dk_name": "Yuki Bhambri", "fd_name": "Yuki Bhambri", "pinn_name": "Yuki Bhambri", "player": 6012}}, {"model": "tennis.alias", "pk": 524, "fields": {"dk_name": "Stefan Kozlov", "fd_name": "Stefan Kozlov", "pinn_name": "Stefan Kozlov", "player": 11563}}, {"model": "tennis.alias", "pk": 525, "fields": {"dk_name": "Robin Montgomery", "fd_name": "Robin Montgomery", "pinn_name": "Robin Montgomery", "player": 63133}}, {"model": "tennis.alias", "pk": 526, "fields": {"dk_name": "Xinyu Wang", "fd_name": "Xinyu Wang", "pinn_name": "Xinyu Wang", "player": 51640}}, {"model": "tennis.alias", "pk": 527, "fields": {"dk_name": "Grace Min", "fd_name": "Grace Min", "pinn_name": "Grace Min", "player": 24385}}, {"model": "tennis.alias", "pk": 528, "fields": {"dk_name": "Giulio Zeppieri", "fd_name": "Giulio Zeppieri", "pinn_name": "Giulio Zeppieri", "player": 84253}}, {"model": "tennis.alias", "pk": 529, "fields": {"dk_name": "Desirae Krawczyk", "fd_name": "Desirae Krawczyk", "pinn_name": "Desirae Krawczyk", "player": 49977}}, {"model": "tennis.alias", "pk": 530, "fields": {"dk_name": "Asia Muhammad", "fd_name": "Asia Muhammad", "pinn_name": "Asia Muhammad", "player": null}}, {"model": "tennis.alias", "pk": 531, "fields": {"dk_name": "Gabriela Talaba", "fd_name": "Gabriela Talaba", "pinn_name": "Gabriela Talaba", "player": 42047}}, {"model": "tennis.alias", "pk": 532, "fields": {"dk_name": "Daniela Seguel", "fd_name": "Daniela Seguel", "pinn_name": "Daniela Seguel", "player": 31456}}, {"model": "tennis.alias", "pk": 533, "fields": {"dk_name": "Jessica Plazas", "fd_name": "Jessica Plazas", "pinn_name": "Jessica Plazas", "player": 51675}}, {"model": "tennis.alias", "pk": 534, "fields": {"dk_name": "Nuria Parrizas Diaz", "fd_name": "Nuria Parrizas-Diaz", "pinn_name": "Nuria Parrizas-Diaz", "player": 26352}}, {"model": "tennis.alias", "pk": 535, "fields": {"dk_name": "Federico Gaio", "fd_name": "Federico Gaio", "pinn_name": "Federico Gaio", "player": 5929}}, {"model": "tennis.alias", "pk": 536, "fields": {"dk_name": "Tereza Mrdeza", "fd_name": "Tereza Mrdeza", "pinn_name": "Tereza Mrdeza", "player": 24742}}, {"model": "tennis.alias", "pk": 537, "fields": {"dk_name": "Nastasja Mariana Schunk", "fd_name": "Nastasja Mariana Schunk", "pinn_name": "Nastasja M Schunk", "player": null}}, {"model": "tennis.alias", "pk": 538, "fields": {"dk_name": "Elena Vesnina", "fd_name": "Elena Vesnina", "pinn_name": "Elena Vesnina", "player": 22341}}, {"model": "tennis.alias", "pk": 539, "fields": {"dk_name": "Ekaterine Gorgodze", "fd_name": "Ekaterine Gorgodze", "pinn_name": "Ekaterine Gorgodze", "player": 24414}}, {"model": "tennis.alias", "pk": 540, "fields": {"dk_name": "Alessandro Giannessi", "fd_name": "Alessandro Giannessi", "pinn_name": "Alessandro Giannessi", "player": 5550}}, {"model": "tennis.alias", "pk": 541, "fields": {"dk_name": "Enzo Couacaud", "fd_name": "Enzo Couacaud", "pinn_name": "Enzo Couacaud", "player": 11490}}, {"model": "tennis.alias", "pk": 542, "fields": {"dk_name": "Zhizhen Zhang", "fd_name": "Zhizhen Zhang", "pinn_name": "Zhizhen Zhang", "player": 11176}}, {"model": "tennis.alias", "pk": 543, "fields": {"dk_name": "Daniel Masur", "fd_name": "Daniel Masur", "pinn_name": "Daniel Masur", "player": 9040}}, {"model": "tennis.alias", "pk": 544, "fields": {"dk_name": "Emma Raducanu", "fd_name": "Emma Raducanu", "pinn_name": "Emma Raducanu", "player": 61438}}, {"model": "tennis.alias", "pk": 545, "fields": {"dk_name": "Rebecca Marino", "fd_name": "Rebecca Marino", "pinn_name": "Rebecca Marino", "player": 22637}}, {"model": "tennis.alias", "pk": 546, "fields": {"dk_name": "Sam Riffice", "fd_name": "Sam Riffice", "pinn_name": "Sam Riffice", "player": 71920}}, {"model": "tennis.alias", "pk": 547, "fields": {"dk_name": "Dalma Galfi", "fd_name": "Dalma Galfi", "pinn_name": "Dalma Galfi", "player": 46667}}, {"model": "tennis.alias", "pk": 548, "fields": {"dk_name": "Emilio Nava", "fd_name": "Emilio Nava", "pinn_name": "Emilio Nava", "player": 85118}}, {"model": "tennis.alias", "pk": 549, "fields": {"dk_name": "Zachary Svajda", "fd_name": "Zachary Svajda", "pinn_name": "Zachary Svajda", "player": 87274}}, {"model": "tennis.alias", "pk": 550, "fields": {"dk_name": "Katie Volynets", "fd_name": "Katie Volynets", "pinn_name": "Katie Volynets", "player": 60291}}, {"model": "tennis.alias", "pk": 551, "fields": {"dk_name": "Ashlyn Krueger", "fd_name": "Ashlyn Krueger", "pinn_name": "Ashlyn Krueger", "player": 63141}}, {"model": "tennis.alias", "pk": 552, "fields": {"dk_name": "Qinwen Zheng", "fd_name": "Qinwen Zheng", "pinn_name": "Qinwen Zheng", "player": 61355}}, {"model": "tennis.alias", "pk": 553, "fields": {"dk_name": "Viktor Durasovic", "fd_name": "Viktor Durasovic", "pinn_name": "Viktor Durasovic", "player": 33264}}, {"model": "tennis.alias", "pk": 554, "fields": {"dk_name": "Jaqueline Adina Cristian", "fd_name": "Jaqueline Cristian", "pinn_name": "Jaqueline Cristian", "player": 42788}}, {"model": "tennis.alias", "pk": 555, "fields": {"dk_name": "Panna Udvardy", "fd_name": "Panna Udvardy", "pinn_name": "Panna Udvardy", "player": 51191}}, {"model": "tennis.alias", "pk": 556, "fields": {"dk_name": "Cristina Bucsa", "fd_name": "Cristina Bucsa", "pinn_name": "Cristina Bucsa", "player": 46795}}, {"model": "tennis.alias", "pk": 557, "fields": {"dk_name": "Maryna Zanevska", "fd_name": "Maryna Zanevska", "pinn_name": "Maryna Zanevska", "player": 24680}}, {"model": "tennis.alias", "pk": 558, "fields": {"dk_name": "Lucia Bronzetti", "fd_name": "Lucia Bronzetti", "pinn_name": "Lucia Bronzetti", "player": 48285}}, {"model": "tennis.alias", "pk": 559, "fields": {"dk_name": "Jiri Lehecka", "fd_name": "Jiri Lehecka", "pinn_name": "Jiri Lehecka", "player": 86958}}, {"model": "tennis.alias", "pk": 560, "fields": {"dk_name": "Emina Bektas", "fd_name": "Emina Bektas", "pinn_name": "Emina Bektas", "player": 42896}}, {"model": "tennis.alias", "pk": 561, "fields": {"dk_name": "Anna Bondar", "fd_name": "Anna Bondar", "pinn_name": "Anna Bondar", "player": 48143}}, {"model": "tennis.alias", "pk": 562, "fields": {"dk_name": "Su Jeong Jang", "fd_name": "Su Jeong Jang", "pinn_name": "Su Jeong Jang", "player": 27965}}]